{
  "10": {
    "report_string": "# 각진 얼굴형에 적합한 스타일 커뮤니티\n\n이 커뮤니티는 각진 얼굴형에 어울리는 다양한 헤어스타일을 중심으로 구성되어 있으며, 부드러운 커버와 볼륨감을 제공하는 스타일들이 포함되어 있습니다. 애즈펌과 같은 남성 스타일부터 태슬 컷과 같은 다양한 조합까지, 각진 얼굴형에 특화된 추천 사항들이 돋보입니다.\n\n## 애즈펌의 부드러운 커버링 효과\n\n애즈펌은 각진 얼굴형을 부드럽게 커버하고 풍성한 볼륨감을 제공하는 남성 스타일로, 각이 진 턱선이나 광대뼈를 시각적으로 완화하는 데 효과적입니다. 이 스타일은 특히 남성들이 부담 없이 시도할 수 있는 트렌디한 선택입니다.\n\n## 가르마펌과 각진 얼굴형의 상호 보완성\n\n가르마펌은 각진 얼굴형을 부드럽게 보완하여 자연스러운 조화를 형성합니다. 이 스타일은 얼굴의 구조를 잘 드러내면서도 부드러운 이미지를 주어 다양한 사회적 상황에 적합합니다. 때문에 남성 고객 사이에서 높인 선호도를 기록하고 있습니다.\n\n## 태슬 컷의 얼굴형 적합성\n\n태슬 컷은 각진 얼굴형에도 잘 어울리며 스타일링의 다양성을 제공합니다. 이 스타일은 다양한 얼굴형과 조합하여 더 개성 있게 표현할 수 있는 장점이 있습니다. 이러한 특성 덕분에 다양한 고객층에게 추천하기 좋은 선택입니다.\n\n## 커뮤니티의 스타일 추천 범위\n\n각진 얼굴형에 맞춘 스타일들은 이미지 관리와 관련하여 서로 보완적인 효과를 발휘합니다. 다양한 스타일 조합을 통해 고객은 개성과 선호를 더욱 반영한 헤어스타일링을 할 수 있습니다. 이는 고객 만족도를 높이는 요소로 작용합니다.",
    "report_json": {
      "title": "각진 얼굴형에 적합한 스타일 커뮤니티",
      "summary": "이 커뮤니티는 각진 얼굴형에 어울리는 다양한 헤어스타일을 중심으로 구성되어 있으며, 부드러운 커버와 볼륨감을 제공하는 스타일들이 포함되어 있습니다. 애즈펌과 같은 남성 스타일부터 태슬 컷과 같은 다양한 조합까지, 각진 얼굴형에 특화된 추천 사항들이 돋보입니다.",
      "rating": 7.0,
      "rating_explanation": "각진 얼굴형에 초점을 맞춘 스타일들이 포함되어 있어 특정 고객층에서 인기를 끌 수 있지만, 상대적으로 제한된 스타일 범위 때문에 높은 점수를 부여하지 않았습니다.",
      "findings": [
        {
          "summary": "애즈펌의 부드러운 커버링 효과",
          "explanation": "애즈펌은 각진 얼굴형을 부드럽게 커버하고 풍성한 볼륨감을 제공하는 남성 스타일로, 각이 진 턱선이나 광대뼈를 시각적으로 완화하는 데 효과적입니다. 이 스타일은 특히 남성들이 부담 없이 시도할 수 있는 트렌디한 선택입니다."
        },
        {
          "summary": "가르마펌과 각진 얼굴형의 상호 보완성",
          "explanation": "가르마펌은 각진 얼굴형을 부드럽게 보완하여 자연스러운 조화를 형성합니다. 이 스타일은 얼굴의 구조를 잘 드러내면서도 부드러운 이미지를 주어 다양한 사회적 상황에 적합합니다. 때문에 남성 고객 사이에서 높인 선호도를 기록하고 있습니다."
        },
        {
          "summary": "태슬 컷의 얼굴형 적합성",
          "explanation": "태슬 컷은 각진 얼굴형에도 잘 어울리며 스타일링의 다양성을 제공합니다. 이 스타일은 다양한 얼굴형과 조합하여 더 개성 있게 표현할 수 있는 장점이 있습니다. 이러한 특성 덕분에 다양한 고객층에게 추천하기 좋은 선택입니다."
        },
        {
          "summary": "커뮤니티의 스타일 추천 범위",
          "explanation": "각진 얼굴형에 맞춘 스타일들은 이미지 관리와 관련하여 서로 보완적인 효과를 발휘합니다. 다양한 스타일 조합을 통해 고객은 개성과 선호를 더욱 반영한 헤어스타일링을 할 수 있습니다. 이는 고객 만족도를 높이는 요소로 작용합니다."
        }
      ]
    },
    "level": 1,
    "title": "Cluster 10",
    "edges": [
      [
        "\"각진 얼굴형\"",
        "\"애즈펌\""
      ],
      [
        "\"가르마펌\"",
        "\"각진 얼굴형\""
      ],
      [
        "\"각진 얼굴형\"",
        "\"태슬 컷\""
      ]
    ],
    "nodes": [
      "\"애즈펌\"",
      "\"각진 얼굴형\""
    ],
    "chunk_ids": [
      "chunk-6c4423bbdfde7099b7dd10cf79466327",
      "chunk-6537c051bb955b20213bcfacafe0ae23"
    ],
    "occurrence": 0.5,
    "sub_communities": []
  },
  "15": {
    "report_string": "# 부드러운 웨이브와 둥근 얼굴형 스타일 커뮤니티\n\n이 커뮤니티는 둥근 얼굴형을 가진 이들에게 적합한 부드러운 웨이브와 관련된 다양한 헤어 스타일 요소로 구성되어 있습니다. 둥근 얼굴형에 맞춰 조화롭게 디자인된 스타일들이 강조되며, 이러한 조합은 얼굴형을 보완하는 측면에서 주목받고 있습니다.\n\n## 둥근 얼굴형에 부드러운 웨이브의 효과\n\n둥근 얼굴형을 가진 사람에게 부드러운 웨이브는 얼굴을 갸름해 보이게 하는 효과가 있습니다. 부드러운 웨이브는 볼륨감을 만들어주고 얼굴의 각을 부드럽게 감싸줘 더욱 매력적인 이미지를 연출하게 도와줍니다.\n\n## 레이어드펌의 자연스러운 웨이브 강조\n\n레이어드펌은 자연스러운 부드러운 웨이브를 더욱 돋보이게 합니다. 이 펌 스타일은 털어내기 쉬우며 자연스러운 흐름을 제공하여 스타일링할 때 편리하고, 둥근 얼굴형을 강조하는 데 효과적입니다.\n\n## 태슬 컷과 둥근 얼굴형 상호작용\n\n태슬 컷은 둥근 얼굴형보다는 각진 얼굴형이나 날카로운 인상에 더 잘 어울리는 스타일입니다. 이는 둥근 얼굴형을 가진 사람들에게는 추천되지 않지만, 각이 진 얼굴형을 가진 고객들에게는 매력적으로 보여줄 수 있습니다.\n\n## 부드러운 웨이브의 대중적인 인기\n\n부드러운 웨이브는 현재 머리 스타일 중에서 인기 있는 선택지로, 다양한 얼굴형과 스타일에 잘 적용될 수 있어 대중적인 매력을 지니고 있습니다. 이는 고객들에게 고급스러움과 스타일을 동시에 제공합니다.",
    "report_json": {
      "title": "부드러운 웨이브와 둥근 얼굴형 스타일 커뮤니티",
      "summary": "이 커뮤니티는 둥근 얼굴형을 가진 이들에게 적합한 부드러운 웨이브와 관련된 다양한 헤어 스타일 요소로 구성되어 있습니다. 둥근 얼굴형에 맞춰 조화롭게 디자인된 스타일들이 강조되며, 이러한 조합은 얼굴형을 보완하는 측면에서 주목받고 있습니다.",
      "rating": 7.5,
      "rating_explanation": "부드러운 웨이브는 둥근 얼굴형에 잘 어울리며, 다양한 스타일과의 조화로 인해 인기가 높아지고 있습니다.",
      "findings": [
        {
          "summary": "둥근 얼굴형에 부드러운 웨이브의 효과",
          "explanation": "둥근 얼굴형을 가진 사람에게 부드러운 웨이브는 얼굴을 갸름해 보이게 하는 효과가 있습니다. 부드러운 웨이브는 볼륨감을 만들어주고 얼굴의 각을 부드럽게 감싸줘 더욱 매력적인 이미지를 연출하게 도와줍니다."
        },
        {
          "summary": "레이어드펌의 자연스러운 웨이브 강조",
          "explanation": "레이어드펌은 자연스러운 부드러운 웨이브를 더욱 돋보이게 합니다. 이 펌 스타일은 털어내기 쉬우며 자연스러운 흐름을 제공하여 스타일링할 때 편리하고, 둥근 얼굴형을 강조하는 데 효과적입니다."
        },
        {
          "summary": "태슬 컷과 둥근 얼굴형 상호작용",
          "explanation": "태슬 컷은 둥근 얼굴형보다는 각진 얼굴형이나 날카로운 인상에 더 잘 어울리는 스타일입니다. 이는 둥근 얼굴형을 가진 사람들에게는 추천되지 않지만, 각이 진 얼굴형을 가진 고객들에게는 매력적으로 보여줄 수 있습니다."
        },
        {
          "summary": "부드러운 웨이브의 대중적인 인기",
          "explanation": "부드러운 웨이브는 현재 머리 스타일 중에서 인기 있는 선택지로, 다양한 얼굴형과 스타일에 잘 적용될 수 있어 대중적인 매력을 지니고 있습니다. 이는 고객들에게 고급스러움과 스타일을 동시에 제공합니다."
        }
      ]
    },
    "level": 1,
    "title": "Cluster 15",
    "edges": [
      [
        "\"둥근 얼굴형\"",
        "\"부드러운 웨이브\""
      ],
      [
        "\"둥근 얼굴형\"",
        "\"태슬 컷\""
      ],
      [
        "\"레이어드펌\"",
        "\"부드러운 웨이브\""
      ]
    ],
    "nodes": [
      "\"부드러운 웨이브\"",
      "\"둥근 얼굴형\""
    ],
    "chunk_ids": [
      "chunk-6c4423bbdfde7099b7dd10cf79466327",
      "chunk-3a88d84a6b27608aa907ee80770e479c"
    ],
    "occurrence": 0.5,
    "sub_communities": []
  },
  "13": {
    "report_string": "# 중단발 스타일 커뮤니티\n\n이 커뮤니티는 중단발과 다양한 스타일 요소인 가벼운 웨이브 및 겹겹이 레이어링을 중심으로 구성되어 있으며, 서로의 조화를 통해 자연스럽고 매력적인 헤어스타일을 제공합니다. 중단발은 다양한 스타일링과 조합으로 많은 인기를 끌고 있습니다.\n\n## 중단발의 자연스러운 매력\n\n중단발은 어깨까지 오는 길이로 가볍고 부드러운 느낌을 제공합니다. 이 스타일은 다양한 얼굴형에 잘 어울리며, 여러 스타일링 방법이 가능한 장점이 있습니다. 특히, 일상적인 스타일링에 적합하여 유지 관리가 용이한 점이 매력적입니다.\n\n## 가벼운 웨이브의 매력\n\n가벼운 웨이브는 중단발과 잘 어우러져 자연스럽고 부드러운 느낌을 강조합니다. 이 조합은 머리에 경량감을 더하며, 지나치지 않은 부드러운 컬로 고객에게 매력적인 이미지를 제공합니다. 이러한 스타일은 다양한 분위기에 맞출 수 있어 유연성이 큽니다.\n\n## 겹겹이 레이어링을 통한 볼륨감\n\n겹겹이 레이어링은 중단발에서 자연스러운 웨이브를 연출하는 데 도움을 주며, 볼륨감과 개성을 더욱 강조합니다. 이 스타일링은 머리가 더욱 풍성해 보이게 하며, 다양한 연출 방법이 가능하게 합니다. 특히, 부드러운 곱슬이나 웨이브와 결합하면 아주 인기 있는 조합이 됩니다.\n\n## 중간머리 굵은 컬펌과의 조화\n\n중간머리 굵은 컬펌은 중단발과 잘 어울려 매력적인 스타일링 선택지를 제공합니다. 이 조합은 중단발이 가져다주는 자연스러운 느낌과 컬펌의 화려함을 결합하여, 특히 특별한 날에 적합한 스타일이 됩니다. 볼륨감 있는 스타일을 원하고 싶은 고객에게 추천할 수 있습니다.",
    "report_json": {
      "title": "중단발 스타일 커뮤니티",
      "summary": "이 커뮤니티는 중단발과 다양한 스타일 요소인 가벼운 웨이브 및 겹겹이 레이어링을 중심으로 구성되어 있으며, 서로의 조화를 통해 자연스럽고 매력적인 헤어스타일을 제공합니다. 중단발은 다양한 스타일링과 조합으로 많은 인기를 끌고 있습니다.",
      "rating": 8.0,
      "rating_explanation": "중단발 및 그와 관련된 스타일 요소가 많은 트렌드에 맞춰 추천되고 있어 높은 점수를 부여했습니다.",
      "findings": [
        {
          "summary": "중단발의 자연스러운 매력",
          "explanation": "중단발은 어깨까지 오는 길이로 가볍고 부드러운 느낌을 제공합니다. 이 스타일은 다양한 얼굴형에 잘 어울리며, 여러 스타일링 방법이 가능한 장점이 있습니다. 특히, 일상적인 스타일링에 적합하여 유지 관리가 용이한 점이 매력적입니다."
        },
        {
          "summary": "가벼운 웨이브의 매력",
          "explanation": "가벼운 웨이브는 중단발과 잘 어우러져 자연스럽고 부드러운 느낌을 강조합니다. 이 조합은 머리에 경량감을 더하며, 지나치지 않은 부드러운 컬로 고객에게 매력적인 이미지를 제공합니다. 이러한 스타일은 다양한 분위기에 맞출 수 있어 유연성이 큽니다."
        },
        {
          "summary": "겹겹이 레이어링을 통한 볼륨감",
          "explanation": "겹겹이 레이어링은 중단발에서 자연스러운 웨이브를 연출하는 데 도움을 주며, 볼륨감과 개성을 더욱 강조합니다. 이 스타일링은 머리가 더욱 풍성해 보이게 하며, 다양한 연출 방법이 가능하게 합니다. 특히, 부드러운 곱슬이나 웨이브와 결합하면 아주 인기 있는 조합이 됩니다."
        },
        {
          "summary": "중간머리 굵은 컬펌과의 조화",
          "explanation": "중간머리 굵은 컬펌은 중단발과 잘 어울려 매력적인 스타일링 선택지를 제공합니다. 이 조합은 중단발이 가져다주는 자연스러운 느낌과 컬펌의 화려함을 결합하여, 특히 특별한 날에 적합한 스타일이 됩니다. 볼륨감 있는 스타일을 원하고 싶은 고객에게 추천할 수 있습니다."
        }
      ]
    },
    "level": 1,
    "title": "Cluster 13",
    "edges": [
      [
        "\"중간머리 굵은 컬펌\"",
        "\"중단발\""
      ],
      [
        "\"겹겹이 레이어링\"",
        "\"중단발\""
      ],
      [
        "\"가벼운 웨이브\"",
        "\"중단발\""
      ]
    ],
    "nodes": [
      "\"겹겹이 레이어링\"",
      "\"가벼운 웨이브\"",
      "\"중단발\""
    ],
    "chunk_ids": [
      "chunk-66b882c32678c93fbdaac53754151003",
      "chunk-3a88d84a6b27608aa907ee80770e479c",
      "chunk-c133af03a51e41eab158f1bb61816b50"
    ],
    "occurrence": 0.75,
    "sub_communities": []
  },
  "19": {
    "report_string": "# 레이어드컷 컬펌 스타일 커뮤니티\n\n이 커뮤니티는 레이어드컷 컬펌을 중심으로 다양한 헤어 스타일링 요소들이 조합되어 구성되어 있습니다. 이 스타일은 여성들 사이에서 인기가 있으며, 모발 손상 최소화와 자연스러운 볼륨감, 다양한 모발 유형과 잘 어울리는 특성을 가지고 있습니다.\n\n## 레이어드컷 컬펌의 볼륨감과 스타일 풍부성\n\n레이어드컷 컬펌은 볼륨감을 더해주는 효과가 뛰어나며, 풍성한 스타일을 연출할 수 있습니다. 이 조합은 자연스러운 컬을 형성하여 헤어 스타일에 고급스러운 이미지를 부여하며, 다양한 자리에서 잘 어울립니다.\n\n## 자연스러운 컬과 고급스러운 스타일의 조화\n\n레이어드컷 컬펌은 자연스러운 컬과 잘 어우러져 세련된 느낌을 줍니다. 이 스타일은 중요하게 생각되는 다양한 사회적 장소에서 인기가 있으며, 특히 직장인들 사이에서 많이 추천됩니다.\n\n## 모발 손상 최소화 효과\n\n레이어드컷 컬펌은 모발 손상을 최소화하는 특성이 있어 건강한 모발 상태를 유지하는 데 도움을 줍니다. 이는 스타일링 제품을 사용할 때도 부담이 덜하고, 장기적인 측면에서 모발 건강을 지킬 수 있습니다.\n\n## 다양한 모발 유형과의 조화\n\n이 스타일은 반곱슬 모발과 보통 두께의 모발에 특히 잘 어울리며, 다양한 모발 유형에 적합합니다. 따라서 스타일링 시 고객의 모발 특성을 고려하여 적절한 조합을 추천할 수 있습니다.\n\n## 겨울철 모발 관리에 적합\n\n겨울철에는 건조한 날씨로 인한 모발의 손상이 우려되는데, 레이어드컷 컬펌은 겨울철에도 효과적인 관리가 가능하여 이 시기에 추천될 수 있는 스타일입니다.\n\n## 손질 난이도와 스타일링 편리함\n\n레이어드컷 컬펌은 상대적으로 손질이 용이하여 일상적인 스타일링에 적합합니다. 바쁜 현대인들에게 이상적인 스타일로, 부지런한 스타일링 방식을 선호하는 고객에게 추천됩니다.\n\n## 여성들 사이에서의 인기도\n\n레이어드컷 컬펌은 주로 여성들 사이에서 인기 있는 선택으로 간편하면서도 세련된 스타일을 찾는 고객들에게 매력적으로 다가옵니다. 이는 여성 고객층이 넓고 다양하며, 꾸준한 추천을 받는 이유이기도 합니다.\n\n## 짜임새 있는 머리 연출 가능\n\n이 스타일은 짜임새 있는 머리를 연출하는 데 도움을 주어 깔끔한 인상을 줍니다. 스타일링을 위해 추가적인 레이어를 더할 경우 더욱 깊이 있는 질감을 제공할 수 있으며, 이는 고객에게 더욱 세련된 옵션을 제안할 수 있게 합니다.",
    "report_json": {
      "title": "레이어드컷 컬펌 스타일 커뮤니티",
      "summary": "이 커뮤니티는 레이어드컷 컬펌을 중심으로 다양한 헤어 스타일링 요소들이 조합되어 구성되어 있습니다. 이 스타일은 여성들 사이에서 인기가 있으며, 모발 손상 최소화와 자연스러운 볼륨감, 다양한 모발 유형과 잘 어울리는 특성을 가지고 있습니다.",
      "rating": 9.5,
      "rating_explanation": "레이어드컷 컬펌이 제공하는 스타일링의 용이함과 다양한 모발 특성과의 유연성이 높은 인기를 얻고 있으므로 높은 점수를 부여했습니다.",
      "findings": [
        {
          "summary": "레이어드컷 컬펌의 볼륨감과 스타일 풍부성",
          "explanation": "레이어드컷 컬펌은 볼륨감을 더해주는 효과가 뛰어나며, 풍성한 스타일을 연출할 수 있습니다. 이 조합은 자연스러운 컬을 형성하여 헤어 스타일에 고급스러운 이미지를 부여하며, 다양한 자리에서 잘 어울립니다."
        },
        {
          "summary": "자연스러운 컬과 고급스러운 스타일의 조화",
          "explanation": "레이어드컷 컬펌은 자연스러운 컬과 잘 어우러져 세련된 느낌을 줍니다. 이 스타일은 중요하게 생각되는 다양한 사회적 장소에서 인기가 있으며, 특히 직장인들 사이에서 많이 추천됩니다."
        },
        {
          "summary": "모발 손상 최소화 효과",
          "explanation": "레이어드컷 컬펌은 모발 손상을 최소화하는 특성이 있어 건강한 모발 상태를 유지하는 데 도움을 줍니다. 이는 스타일링 제품을 사용할 때도 부담이 덜하고, 장기적인 측면에서 모발 건강을 지킬 수 있습니다."
        },
        {
          "summary": "다양한 모발 유형과의 조화",
          "explanation": "이 스타일은 반곱슬 모발과 보통 두께의 모발에 특히 잘 어울리며, 다양한 모발 유형에 적합합니다. 따라서 스타일링 시 고객의 모발 특성을 고려하여 적절한 조합을 추천할 수 있습니다."
        },
        {
          "summary": "겨울철 모발 관리에 적합",
          "explanation": "겨울철에는 건조한 날씨로 인한 모발의 손상이 우려되는데, 레이어드컷 컬펌은 겨울철에도 효과적인 관리가 가능하여 이 시기에 추천될 수 있는 스타일입니다."
        },
        {
          "summary": "손질 난이도와 스타일링 편리함",
          "explanation": "레이어드컷 컬펌은 상대적으로 손질이 용이하여 일상적인 스타일링에 적합합니다. 바쁜 현대인들에게 이상적인 스타일로, 부지런한 스타일링 방식을 선호하는 고객에게 추천됩니다."
        },
        {
          "summary": "여성들 사이에서의 인기도",
          "explanation": "레이어드컷 컬펌은 주로 여성들 사이에서 인기 있는 선택으로 간편하면서도 세련된 스타일을 찾는 고객들에게 매력적으로 다가옵니다. 이는 여성 고객층이 넓고 다양하며, 꾸준한 추천을 받는 이유이기도 합니다."
        },
        {
          "summary": "짜임새 있는 머리 연출 가능",
          "explanation": "이 스타일은 짜임새 있는 머리를 연출하는 데 도움을 주어 깔끔한 인상을 줍니다. 스타일링을 위해 추가적인 레이어를 더할 경우 더욱 깊이 있는 질감을 제공할 수 있으며, 이는 고객에게 더욱 세련된 옵션을 제안할 수 있게 합니다."
        }
      ]
    },
    "level": 1,
    "title": "Cluster 19",
    "edges": [
      [
        "\"레이어드컷 컬펌\"",
        "\"손질 난이도 보통\""
      ],
      [
        "\"레이어드컷 컬펌\"",
        "\"부지런한 스타일링\""
      ],
      [
        "\"레이어드컷 컬펌\"",
        "\"여성들\""
      ],
      [
        "\"가벼운 헤어 제품\"",
        "\"레이어드컷 컬펌\""
      ],
      [
        "\"레이어드컷 컬펌\"",
        "\"보통 두께의 모발\""
      ],
      [
        "\"레이어드컷 컬펌\"",
        "\"반곱슬 모발\""
      ],
      [
        "\"레이어드컷 컬펌\"",
        "\"모발 손상 최소화\""
      ],
      [
        "\"레이어드컷 컬펌\"",
        "\"부슬부슬한 모발\""
      ],
      [
        "\"레이어드컷 컬펌\"",
        "\"자연스러운 분위기\""
      ],
      [
        "\"레이어드컷 컬펌\"",
        "\"볼륨감\""
      ],
      [
        "\"긴머리\"",
        "\"레이어드컷 컬펌\""
      ],
      [
        "\"레이어드컷 컬펌\"",
        "\"자연스러운 컬\""
      ],
      [
        "\"레이어드컷 컬펌\"",
        "\"세련된 느낌\""
      ],
      [
        "\"레이어드컷 컬펌\"",
        "\"부시시한 머리카락\""
      ],
      [
        "\"드라이어\"",
        "\"레이어드컷 컬펌\""
      ],
      [
        "\"레이어드컷 컬펌\"",
        "\"직장인\""
      ],
      [
        "\"겨울철 모발 관리\"",
        "\"레이어드컷 컬펌\""
      ],
      [
        "\"레이어드컷 컬펌\"",
        "\"짜임새 있는 머리\""
      ],
      [
        "\"레이어드컷 컬펌\"",
        "\"추가적인 레이어\""
      ]
    ],
    "nodes": [
      "\"짜임새 있는 머리\"",
      "\"부지런한 스타일링\"",
      "\"반곱슬 모발\"",
      "\"겨울철 모발 관리\"",
      "\"부슬부슬한 모발\"",
      "\"자연스러운 분위기\"",
      "\"보통 두께의 모발\"",
      "\"가벼운 헤어 제품\"",
      "\"여성들\"",
      "\"긴머리\"",
      "\"추가적인 레이어\"",
      "\"손질 난이도 보통\"",
      "\"레이어드컷 컬펌\"",
      "\"부시시한 머리카락\"",
      "\"직장인\"",
      "\"드라이어\""
    ],
    "chunk_ids": [
      "chunk-c133af03a51e41eab158f1bb61816b50"
    ],
    "occurrence": 0.25,
    "sub_communities": []
  },
  "20": {
    "report_string": "# 레이어드 컬펌과 자연스러운 컬 스타일 커뮤니티\n\n이 커뮤니티는 레이어드 컬펌을 중심으로 자연스러운 컬과 볼륨 스프레이를 활용하여 고급스러운 헤어스타일을 만드는 데 집중하고 있습니다. 각 요소가 다른 스타일과 적절히 어우러져 자연스럽고 부드러운 웨이브 형태를 강조하며, 함께 사용되는 제품들을 통해 효과적인 스타일링을 지원합니다.\n\n## 레이어드 컬펌과 자연스러운 컬의 조화\n\n레이어드 컬펌은 자연스러운 컬을 만들어 주며, 두 스타일이 결합되면 고급스러운 이미지와 더불어 자연스러운 웨이브를 형성합니다. 이는 현대적인 헤어스타일링에서 매우 선호되는 요소로, 많은 사람들이 자연스러운 룩을 원할 때 자주 선택하는 스타일입니다.\n\n## 볼륨 스프레이의 효과적인 활용\n\n볼륨 스프레이는 레이어드 컬펌과 함께 사용했을 때 효과를 극대화합니다. 이 제품은 가벼운 질감을 잃지 않으면서도 머리에 볼륨을 추가해주어, 전체적인 스타일링의 완성도를 높여줍니다. 많은 사용자들이 이를 통해 풍성한 스타일을 연출할 수 있습니다.\n\n## 고급스러운 이미지 제공\n\n레이어드 컬펌과 자연스러운 컬 조합은 부자연스럽지 않고 매끄러운 이미지를 제공하여, 다양한 스타일링 상황에서 적절하게 선택될 수 있습니다. 이로 인해 고객들은 결혼식이나 특별한 행사 등에서 자주 선택하게 되는 조합입니다.\n\n## 스타일 조합의 유연성\n\n이 커뮤니티의 스타일들은 서로 잘 어울려 다양한 조합으로 활용될 수 있습니다. 레이어드 컬펌이 주를 이루면서도 자연스러운 컬과 볼륨 스프레이를 통해 고객의 다양한 요구에 부응할 수 있는 유연함을 가지고 있습니다.",
    "report_json": {
      "title": "레이어드 컬펌과 자연스러운 컬 스타일 커뮤니티",
      "summary": "이 커뮤니티는 레이어드 컬펌을 중심으로 자연스러운 컬과 볼륨 스프레이를 활용하여 고급스러운 헤어스타일을 만드는 데 집중하고 있습니다. 각 요소가 다른 스타일과 적절히 어우러져 자연스럽고 부드러운 웨이브 형태를 강조하며, 함께 사용되는 제품들을 통해 효과적인 스타일링을 지원합니다.",
      "rating": 7.5,
      "rating_explanation": "레이어드 컬펌과 자연스러운 컬은 조화를 이루며 고급스러운 이미지를 제공하는 인기 있는 조합으로, 특히 스타일링 용이성과 적용 가능성이 높아 높은 점수를 부여했습니다.",
      "findings": [
        {
          "summary": "레이어드 컬펌과 자연스러운 컬의 조화",
          "explanation": "레이어드 컬펌은 자연스러운 컬을 만들어 주며, 두 스타일이 결합되면 고급스러운 이미지와 더불어 자연스러운 웨이브를 형성합니다. 이는 현대적인 헤어스타일링에서 매우 선호되는 요소로, 많은 사람들이 자연스러운 룩을 원할 때 자주 선택하는 스타일입니다."
        },
        {
          "summary": "볼륨 스프레이의 효과적인 활용",
          "explanation": "볼륨 스프레이는 레이어드 컬펌과 함께 사용했을 때 효과를 극대화합니다. 이 제품은 가벼운 질감을 잃지 않으면서도 머리에 볼륨을 추가해주어, 전체적인 스타일링의 완성도를 높여줍니다. 많은 사용자들이 이를 통해 풍성한 스타일을 연출할 수 있습니다."
        },
        {
          "summary": "고급스러운 이미지 제공",
          "explanation": "레이어드 컬펌과 자연스러운 컬 조합은 부자연스럽지 않고 매끄러운 이미지를 제공하여, 다양한 스타일링 상황에서 적절하게 선택될 수 있습니다. 이로 인해 고객들은 결혼식이나 특별한 행사 등에서 자주 선택하게 되는 조합입니다."
        },
        {
          "summary": "스타일 조합의 유연성",
          "explanation": "이 커뮤니티의 스타일들은 서로 잘 어울려 다양한 조합으로 활용될 수 있습니다. 레이어드 컬펌이 주를 이루면서도 자연스러운 컬과 볼륨 스프레이를 통해 고객의 다양한 요구에 부응할 수 있는 유연함을 가지고 있습니다."
        }
      ]
    },
    "level": 1,
    "title": "Cluster 20",
    "edges": [
      [
        "\"레이어드컷 컬펌\"",
        "\"자연스러운 컬\""
      ],
      [
        "\"레이어드 컬펌\"",
        "\"자연스러운 컬\""
      ],
      [
        "\"레이어드 컬펌\"",
        "\"볼륨 스프레이\""
      ]
    ],
    "nodes": [
      "\"자연스러운 컬\"",
      "\"레이어드 컬펌\"",
      "\"볼륨 스프레이\""
    ],
    "chunk_ids": [
      "chunk-aa3286f7d8b8f5afc0b3db44ded13e3f",
      "chunk-c133af03a51e41eab158f1bb61816b50",
      "chunk-3a88d84a6b27608aa907ee80770e479c"
    ],
    "occurrence": 0.75,
    "sub_communities": []
  },
  "21": {
    "report_string": "# 레이어드컷 컬펌과 모발 손상 최소화 커뮤니티\n\n이 커뮤니티는 레이어드컷 컬펌과 관련된 스타일 및 관리 방법을 중심으로 형성된 그룹으로, 모발 손상을 최소화하며 건강한 상태를 유지하는 것에 중점을 둡니다. 이와 함께 스타일링을 위한 적절한 화장품 사용이 중요하다는 점이 강조됩니다.\n\n## 레이어드컷 컬펌의 손상 최소화 효과\n\n레이어드컷 컬펌은 모발 손상을 최소화하는데 특히 유효하며, 이는 고객들이 건강한 머리카락을 유지하며 스타일을 즐길 수 있도록 합니다. 이 기법은 시술과정에서 모발에 가해지는 스트레스를 줄여주어 보다 나은 결과를 가져옵니다.\n\n## 모발 손상 최소화와 화장품의 관계\n\n모발 손상 최소화는 적절한 화장품 사용을 통해 더욱 향상될 수 있습니다. 고객들은 효과적인 스타일링을 위해 손상 최소화를 고려해야 하며, 질 좋은 헤어 제품 사용이 이러한 관리에 필수적이라는 점이 강조됩니다.",
    "report_json": {
      "title": "레이어드컷 컬펌과 모발 손상 최소화 커뮤니티",
      "summary": "이 커뮤니티는 레이어드컷 컬펌과 관련된 스타일 및 관리 방법을 중심으로 형성된 그룹으로, 모발 손상을 최소화하며 건강한 상태를 유지하는 것에 중점을 둡니다. 이와 함께 스타일링을 위한 적절한 화장품 사용이 중요하다는 점이 강조됩니다.",
      "rating": 7.5,
      "rating_explanation": "모발 손상 최소화와 건강한 스타일링을 중시하는 점에서 이 커뮤니티의 중요성이 강조되며, 그에 따른 추천 가능성도 높습니다.",
      "findings": [
        {
          "summary": "레이어드컷 컬펌의 손상 최소화 효과",
          "explanation": "레이어드컷 컬펌은 모발 손상을 최소화하는데 특히 유효하며, 이는 고객들이 건강한 머리카락을 유지하며 스타일을 즐길 수 있도록 합니다. 이 기법은 시술과정에서 모발에 가해지는 스트레스를 줄여주어 보다 나은 결과를 가져옵니다."
        },
        {
          "summary": "모발 손상 최소화와 화장품의 관계",
          "explanation": "모발 손상 최소화는 적절한 화장품 사용을 통해 더욱 향상될 수 있습니다. 고객들은 효과적인 스타일링을 위해 손상 최소화를 고려해야 하며, 질 좋은 헤어 제품 사용이 이러한 관리에 필수적이라는 점이 강조됩니다."
        }
      ]
    },
    "level": 1,
    "title": "Cluster 21",
    "edges": [
      [
        "\"모발 손상 최소화\"",
        "\"화장품 사용\""
      ],
      [
        "\"레이어드컷 컬펌\"",
        "\"모발 손상 최소화\""
      ]
    ],
    "nodes": [
      "\"화장품 사용\"",
      "\"모발 손상 최소화\""
    ],
    "chunk_ids": [
      "chunk-c133af03a51e41eab158f1bb61816b50",
      "chunk-6537c051bb955b20213bcfacafe0ae23"
    ],
    "occurrence": 0.5,
    "sub_communities": []
  },
  "14": {
    "report_string": "# 레이어드펌과 중간머리 굵은 컬펌 공동 스타일 커뮤니티\n\n이 커뮤니티는 레이어드펌과 중간머리 굵은 컬펌으로 구성되어 있으며, 두 스타일은 서로 조화롭게 결합되어 다양한 얼굴형과 머리 굵기에서의 장점을 극대화합니다. 이들 스타일은 자연스러움과 편안한 느낌을 강조하며 개인의 매력을 끌어낼 수 있는 선택지를 제공합니다.\n\n## 레이어드펌과 중간머리 굵은 컬펌의 조합으로 강조되는 볼륨감\n\n레이어드펌과 중간머리 굵은 컬펌은 함께 시술될 때, 각 스타일의 특징을 살려 볼륨감을 극대화합니다. 레이어드펌이 가벼운 층을 더해주고 중간머리 굵은 컬펌이 자연스러운 컬을 형성하여 풍성한 분위기를 연출할 수 있습니다.\n\n## 레이어드펌의 스타일링 효과가 부여하는 동안 효과\n\n레이어드펌은 부드러운 인상을 주는 효과가 있어, 특히 긴 얼굴형의 고객에게 적합합니다. 레이어드펌이 얼굴에 볼륨을 추가하여 부드러운 느낌을 주면서 동안 이미지를 연출할 수 있는 장점이 있습니다.\n\n## 중간머리 굵은 컬펌이 잘 어울리는 특징\n\n중간머리 굵은 컬펌은 얇은 모발에 적합하도록 설계된 스타일로, 자연스럽고 관리하기 쉬운 분위기를 생산하는 데 중점을 둡니다. 이는 특히 쇄골 위에서 중간 길이의 머리에서 최적의 효과를 발휘합니다.\n\n## 깔끔하고 편안한 느낌을 줄 수 있는 중간머리 굵은 컬펌의 특징\n\n중간머리 굵은 컬펌은 고객에게 깔끔하고 편안한 인상을 전달할 수 있는 스타일로 인식되고 있습니다. 이 스타일은 일상적인 느낌을 중시하며, 고객의 삶에 있어 자연스러운 매력을 더할 수 있습니다.",
    "report_json": {
      "title": "레이어드펌과 중간머리 굵은 컬펌 공동 스타일 커뮤니티",
      "summary": "이 커뮤니티는 레이어드펌과 중간머리 굵은 컬펌으로 구성되어 있으며, 두 스타일은 서로 조화롭게 결합되어 다양한 얼굴형과 머리 굵기에서의 장점을 극대화합니다. 이들 스타일은 자연스러움과 편안한 느낌을 강조하며 개인의 매력을 끌어낼 수 있는 선택지를 제공합니다.",
      "rating": 8.0,
      "rating_explanation": "두 스타일은 다양한 고객의 니즈를 충족시키며, 특히 얇은 모발을 가진 고객을 위해 최적화된 추천이 가능하여 높은 인기와 트렌디함을 반영합니다.",
      "findings": [
        {
          "summary": "레이어드펌과 중간머리 굵은 컬펌의 조합으로 강조되는 볼륨감",
          "explanation": "레이어드펌과 중간머리 굵은 컬펌은 함께 시술될 때, 각 스타일의 특징을 살려 볼륨감을 극대화합니다. 레이어드펌이 가벼운 층을 더해주고 중간머리 굵은 컬펌이 자연스러운 컬을 형성하여 풍성한 분위기를 연출할 수 있습니다."
        },
        {
          "summary": "레이어드펌의 스타일링 효과가 부여하는 동안 효과",
          "explanation": "레이어드펌은 부드러운 인상을 주는 효과가 있어, 특히 긴 얼굴형의 고객에게 적합합니다. 레이어드펌이 얼굴에 볼륨을 추가하여 부드러운 느낌을 주면서 동안 이미지를 연출할 수 있는 장점이 있습니다."
        },
        {
          "summary": "중간머리 굵은 컬펌이 잘 어울리는 특징",
          "explanation": "중간머리 굵은 컬펌은 얇은 모발에 적합하도록 설계된 스타일로, 자연스럽고 관리하기 쉬운 분위기를 생산하는 데 중점을 둡니다. 이는 특히 쇄골 위에서 중간 길이의 머리에서 최적의 효과를 발휘합니다."
        },
        {
          "summary": "깔끔하고 편안한 느낌을 줄 수 있는 중간머리 굵은 컬펌의 특징",
          "explanation": "중간머리 굵은 컬펌은 고객에게 깔끔하고 편안한 인상을 전달할 수 있는 스타일로 인식되고 있습니다. 이 스타일은 일상적인 느낌을 중시하며, 고객의 삶에 있어 자연스러운 매력을 더할 수 있습니다."
        }
      ]
    },
    "level": 1,
    "title": "Cluster 14",
    "edges": [
      [
        "\"긴 얼굴형\"",
        "\"레이어드펌\""
      ],
      [
        "\"동안 효과\"",
        "\"레이어드펌\""
      ],
      [
        "\"레이어드펌\"",
        "\"중간머리 굵은 컬펌\""
      ],
      [
        "\"중간머리 굵은 컬펌\"",
        "\"중단발\""
      ],
      [
        "\"깔끔하고 편안한 느낌\"",
        "\"중간머리 굵은 컬펌\""
      ],
      [
        "\"레이어드펌\"",
        "\"얇은 모발\""
      ],
      [
        "\"가슴 길이\"",
        "\"중간머리 굵은 컬펌\""
      ],
      [
        "\"얇은 모발\"",
        "\"중간머리 굵은 컬펌\""
      ],
      [
        "\"레이어드펌\"",
        "\"부드러운 웨이브\""
      ]
    ],
    "nodes": [
      "\"중간머리 굵은 컬펌\"",
      "\"레이어드펌\"",
      "\"깔끔하고 편안한 느낌\"",
      "\"얇은 모발\"",
      "\"가슴 길이\""
    ],
    "chunk_ids": [
      "chunk-3a88d84a6b27608aa907ee80770e479c"
    ],
    "occurrence": 0.25,
    "sub_communities": []
  },
  "9": {
    "report_string": "# 가르마펌 중심의 남성 헤어스타일 커뮤니티\n\n이 커뮤니티는 남성용 가르마펌을 중심으로 다양한 스타일과 기능적 요소들이 조화를 이루며, 다양한 모발 성질과 얼굴형에 적합한 세련된 스타일링을 제공합니다. 가르마펌은 특히 취업 면접, 소개팅과 같은 상황에서 인상을 좌우하는 중요한 스타일로 자리잡고 있습니다.\n\n## 가르마펌의 다목적성\n\n가르마펌은 다양한 얼굴형과 모발 상태에 잘 어울리는 스타일로, 특히 각진 얼굴형과 직모에 적합하다는 특징이 있습니다. 직모를 가진 남성은 가르마펌을 통해 자연스러운 볼륨을 추가할 수 있으며, 각진 얼굴형은 부드러운 인상을 받을 수 있습니다.\n\n## 개인 맞춤형 시술의 중요성\n\n가르마펌은 개인 맞춤형 시술이 가능하여, 각 개인의 얼굴형에 맞춘 스타일링이 가능하다는 점에서 매우 유용합니다. 이는 고객들의 다양한 요구를 충족시키며, 스타일링 과정에서의 만족도를 더욱 높입니다.\n\n## 면접 준비 시 가르마펌의 신뢰감\n\n가르마펌은 면접 준비 시 신뢰감을 줄 수 있는 스타일로 자주 추천됩니다. 단정한 스타일이 면접관에게 긍정적인 인상을 주며, 구직 활동에서의 중요한 요소로 작용합니다.\n\n## 소개팅을 위한 매력적인 인상 제공\n\n가르마펌은 소개팅과 같은 사회적 만남에서 매력적인 인상을 줄 수 있어 많은 남성들에게 선호됩니다. 스타일링이 깔끔하여 첫인상에서 긍정적인 반응을 이끌어낼 수 있습니다.\n\n## 가르마펌과 쉐도우펌의 조화\n\n가르마펌은 쉐도우펌과 함께 사용되어 다양한 컬과 볼륨감을 제공함으로써 스타일의 선택 폭을 넓힙니다. 두 스타일은 각각의 특징을 살리면서도 조화롭게 어우러질 수 있어, 다양한 상황에 적합한 독특한 분위기를 연출합니다.",
    "report_json": {
      "title": "가르마펌 중심의 남성 헤어스타일 커뮤니티",
      "summary": "이 커뮤니티는 남성용 가르마펌을 중심으로 다양한 스타일과 기능적 요소들이 조화를 이루며, 다양한 모발 성질과 얼굴형에 적합한 세련된 스타일링을 제공합니다. 가르마펌은 특히 취업 면접, 소개팅과 같은 상황에서 인상을 좌우하는 중요한 스타일로 자리잡고 있습니다.",
      "rating": 8.5,
      "rating_explanation": "가르마펌은 다양한 털 상태와 얼굴형에 적합하면서도 신뢰감과 세련됨을 줄 수 있어, 남성들의 스타일 선택에 있어서 높은 인기를 끌고 있습니다.",
      "findings": [
        {
          "summary": "가르마펌의 다목적성",
          "explanation": "가르마펌은 다양한 얼굴형과 모발 상태에 잘 어울리는 스타일로, 특히 각진 얼굴형과 직모에 적합하다는 특징이 있습니다. 직모를 가진 남성은 가르마펌을 통해 자연스러운 볼륨을 추가할 수 있으며, 각진 얼굴형은 부드러운 인상을 받을 수 있습니다."
        },
        {
          "summary": "개인 맞춤형 시술의 중요성",
          "explanation": "가르마펌은 개인 맞춤형 시술이 가능하여, 각 개인의 얼굴형에 맞춘 스타일링이 가능하다는 점에서 매우 유용합니다. 이는 고객들의 다양한 요구를 충족시키며, 스타일링 과정에서의 만족도를 더욱 높입니다."
        },
        {
          "summary": "면접 준비 시 가르마펌의 신뢰감",
          "explanation": "가르마펌은 면접 준비 시 신뢰감을 줄 수 있는 스타일로 자주 추천됩니다. 단정한 스타일이 면접관에게 긍정적인 인상을 주며, 구직 활동에서의 중요한 요소로 작용합니다."
        },
        {
          "summary": "소개팅을 위한 매력적인 인상 제공",
          "explanation": "가르마펌은 소개팅과 같은 사회적 만남에서 매력적인 인상을 줄 수 있어 많은 남성들에게 선호됩니다. 스타일링이 깔끔하여 첫인상에서 긍정적인 반응을 이끌어낼 수 있습니다."
        },
        {
          "summary": "가르마펌과 쉐도우펌의 조화",
          "explanation": "가르마펌은 쉐도우펌과 함께 사용되어 다양한 컬과 볼륨감을 제공함으로써 스타일의 선택 폭을 넓힙니다. 두 스타일은 각각의 특징을 살리면서도 조화롭게 어우러질 수 있어, 다양한 상황에 적합한 독특한 분위기를 연출합니다."
        }
      ]
    },
    "level": 1,
    "title": "Cluster 9",
    "edges": [
      [
        "\"가르마펌\"",
        "\"소개팅 준비\""
      ],
      [
        "\"가르마펌\"",
        "\"개인 맞춤형 시술\""
      ],
      [
        "\"가르마펌\"",
        "\"중간 길이의 단발\""
      ],
      [
        "\"가르마펌\"",
        "\"내추럴 가르마펌\""
      ],
      [
        "\"가르마펌\"",
        "\"곱슬 모발\""
      ],
      [
        "\"가르마펌\"",
        "\"계란형 얼굴\""
      ],
      [
        "\"가르마펌\"",
        "\"직모\""
      ],
      [
        "\"가르마펌\"",
        "\"면접 준비\""
      ],
      [
        "\"가르마펌\"",
        "\"볼륨이 부족한 경우\""
      ],
      [
        "\"가는 모발\"",
        "\"가르마펌\""
      ],
      [
        "\"가르마펌\"",
        "\"세련된 인상\""
      ],
      [
        "\"가르마펌\"",
        "\"각진 얼굴형\""
      ],
      [
        "\"가르마펌\"",
        "\"장발\""
      ],
      [
        "\"가르마펌\"",
        "\"쉐도우펌\""
      ]
    ],
    "nodes": [
      "\"곱슬 모발\"",
      "\"내추럴 가르마펌\"",
      "\"중간 길이의 단발\"",
      "\"볼륨이 부족한 경우\"",
      "\"가르마펌\"",
      "\"면접 준비\"",
      "\"쉐도우펌\"",
      "\"세련된 인상\"",
      "\"소개팅 준비\"",
      "\"장발\"",
      "\"개인 맞춤형 시술\""
    ],
    "chunk_ids": [
      "chunk-6537c051bb955b20213bcfacafe0ae23"
    ],
    "occurrence": 0.25,
    "sub_communities": []
  },
  "18": {
    "report_string": "# 부드러운 느낌과 직모 중심 헤어스타일 커뮤니티\n\n이 커뮤니티는 부드러운 느낌과 직모를 중심으로 한 다양한 헤어스타일을 아우릅니다. 리프컷펌, 포마드펌 등의 스타일은 남성과 여성 모두에게 인기가 있으며 서로 연관되어 추천되는 스타일 조합을 형성하고 있습니다.\n\n## 리프컷펌의 인기와 고객 선호\n\n리프컷펌은 특히 부드러운 느낌을 주는 스타일로 고객들 사이에서 높은 선호도를 보입니다. 가벼운 끝처리와 귀 뒤로 넘기는 스타일은 일상적인 착용에 적합해 자주 추천됩니다.\n\n## 포마드펌의 매력\n\n포마드펌은 남성다움과 깔끔함을 강조하는 스타일로, 다양한 가르마 위치에 따라 분위기를 조절할 수 있습니다. 이는 고객의 개성과 필요에 맞춘 스타일링을 가능하게 합니다.\n\n## 직모에 적합한 스타일 조합\n\n가르마펌, 가일컷과 같은 스타일은 직모를 가진 남성들에게 적합하며, 자연스러운 헤어라인을 형성하는 데 효과가 있습니다. 직모에 잘 어울리는 스타일들이 많아 고객의 선택폭이 넓습니다.\n\n## 부드러운 느낌과 관련된 스타일\n\n부드러운 느낌은 다양한 헤어스타일, 특히 포마드펌과 리프컷펌에서 강조됩니다. 이는 고객들이 원하는 편안하고 고급스러운 이미지를 실현하기 위해 필수적인 요소로 작용합니다.\n\n## 스타일 간의 연관성\n\n리프컷펌은 직모와 잘 어울리며, 부드러운 느낌을 주기 때문에 자주 추천됩니다. 또한, 포마드펌과 가일 포마드펌은 스타일적으로 연결되어 있어 고객들에게 상호 추천되는 경우가 많습니다.",
    "report_json": {
      "title": "부드러운 느낌과 직모 중심 헤어스타일 커뮤니티",
      "summary": "이 커뮤니티는 부드러운 느낌과 직모를 중심으로 한 다양한 헤어스타일을 아우릅니다. 리프컷펌, 포마드펌 등의 스타일은 남성과 여성 모두에게 인기가 있으며 서로 연관되어 추천되는 스타일 조합을 형성하고 있습니다.",
      "rating": 7.5,
      "rating_explanation": "부드러운 느낌과 직모에 적합한 스타일들이 많이 포함되어 있어 실용성과 아름다움을 동시에 추구하는 고객들에게 높은 점수를 부여했습니다.",
      "findings": [
        {
          "summary": "리프컷펌의 인기와 고객 선호",
          "explanation": "리프컷펌은 특히 부드러운 느낌을 주는 스타일로 고객들 사이에서 높은 선호도를 보입니다. 가벼운 끝처리와 귀 뒤로 넘기는 스타일은 일상적인 착용에 적합해 자주 추천됩니다."
        },
        {
          "summary": "포마드펌의 매력",
          "explanation": "포마드펌은 남성다움과 깔끔함을 강조하는 스타일로, 다양한 가르마 위치에 따라 분위기를 조절할 수 있습니다. 이는 고객의 개성과 필요에 맞춘 스타일링을 가능하게 합니다."
        },
        {
          "summary": "직모에 적합한 스타일 조합",
          "explanation": "가르마펌, 가일컷과 같은 스타일은 직모를 가진 남성들에게 적합하며, 자연스러운 헤어라인을 형성하는 데 효과가 있습니다. 직모에 잘 어울리는 스타일들이 많아 고객의 선택폭이 넓습니다."
        },
        {
          "summary": "부드러운 느낌과 관련된 스타일",
          "explanation": "부드러운 느낌은 다양한 헤어스타일, 특히 포마드펌과 리프컷펌에서 강조됩니다. 이는 고객들이 원하는 편안하고 고급스러운 이미지를 실현하기 위해 필수적인 요소로 작용합니다."
        },
        {
          "summary": "스타일 간의 연관성",
          "explanation": "리프컷펌은 직모와 잘 어울리며, 부드러운 느낌을 주기 때문에 자주 추천됩니다. 또한, 포마드펌과 가일 포마드펌은 스타일적으로 연결되어 있어 고객들에게 상호 추천되는 경우가 많습니다."
        }
      ]
    },
    "level": 1,
    "title": "Cluster 18",
    "edges": [
      [
        "\"가일 포마드펌\"",
        "\"포마드펌\""
      ],
      [
        "\"리프컷펌\"",
        "\"직모\""
      ],
      [
        "\"부드러운 느낌\"",
        "\"스핀스왈로펌\""
      ],
      [
        "\"가일컷\"",
        "\"직모\""
      ],
      [
        "\"가르마펌\"",
        "\"직모\""
      ],
      [
        "\"부드러운 느낌\"",
        "\"포마드펌\""
      ],
      [
        "\"리프컷펌\"",
        "\"부드러운 느낌\""
      ]
    ],
    "nodes": [
      "\"리프컷펌\"",
      "\"부드러운 느낌\"",
      "\"직모\"",
      "\"포마드펌\""
    ],
    "chunk_ids": [
      "chunk-aa3286f7d8b8f5afc0b3db44ded13e3f",
      "chunk-26f0ef8ea2f7ad3255c67cac5e87a11a",
      "chunk-6537c051bb955b20213bcfacafe0ae23"
    ],
    "occurrence": 0.75,
    "sub_communities": []
  },
  "11": {
    "report_string": "# 가일컷 중심 헤어스타일 커뮤니티\n\n이 커뮤니티는 가일컷을 중심으로 다양한 헤어스타일과 특징들이 조화를 이루며, 스타일링과 관리의 용이성을 강조합니다. 가일컷은 여러 머리 특징과 조화를 이루어 성숙하고 깔끔한 이미지를 만들어낼 수 있는 스타일입니다.\n\n## 가일컷과 굵은 모발의 조화\n\n가일컷은 굵은 모발에 잘 어울리는 스타일로, 두껍고 힘있는 머리카락의 장점을 살려줍니다. 이 스타일은 자연스러운 헤어라인을 형성하여 시원한 느낌을 강화시키며, 깔끔하게 정돈된 인상을 줄 수 있습니다.\n\n## 가일컷의 다운펌 시너지\n\n가일컷은 다운펌과 함께 시술될 때 더욱 깔끔한 댄디 스타일로 연출됩니다. 다운펌은 머리카락의 뿌리를 눌러 부드럽고 자연스러운 스타일을 만들어 주는데, 이 결합으로 인해 더욱 정돈된 느낌을 얻을 수 있습니다.\n\n## 리프팅 효과로 얼굴형 보완\n\n가일컷은 리프팅 효과를 통해 머리의 볼륨감을 높이며, 동시에 얼굴형을 보완하는 특징을 가지고 있습니다. 이로 인해 고객들은 더욱 균형 잡힌 얼굴형을 연출할 수 있으며, 세련된 인상을 심어줄 수 있습니다.\n\n## 성숙하고 깔끔한 이미지 제공\n\n가일컷은 성숙하고 깔끔한 분위기를 주는 스타일 특징이 있어, 사회적이나 직장에서의 분위기를 고려할 때 유용한 선택이 됩니다. 이 스타일은 다양한 연령층에 걸쳐 선호되며, 정돈된 인상이 주요 요구사항인 경우 좋습니다.\n\n## 쉽게 관리할 수 있는 스타일\n\n가일컷은 관리와 스타일링이 용이하다는 장점이 있어 바쁜 현대인들에게 특히 추천할 수 있습니다. 빠르게 스타일을 잡을 수 있고, 일상적인 손질이 덜 필요하다는 점에서 많은 소비자에게 인기를 끌고 있습니다.\n\n## 다양한 앞머리 길이 조절\n\n가일컷은 앞머리의 길이를 조절하여 여러 가지 이미지를 연출할 수 있는 유연성을 제공합니다. 고객의 얼굴형이나 스타일에 따라 길이를 조절하여 맞춤형 스타일링이 가능하며, 다양한 분위기를 시도할 수 있습니다.\n\n## 이마가 넓은 얼굴형에 적합\n\n가일컷은 이마가 넓은 얼굴형에 적합하도록 설계되어 있습니다. 앞머리의 길이를 조절하여 넓은 이마를 부분적으로 가림으로써 전체적인 균형을 잡아 주는 효과가 있습니다.\n\n## 프론트 오픈으로 시원한 느낌 강조\n\n가일컷은 이마를 드러내는 프론트 오픈 스타일을 특징으로 하여 시원한 느낌을 강조합니다. 이는 특히 더운 날씨에 적합하며, 여름철에 인기 있는 스타일로 자리매김하고 있습니다.\n\n## 헤어라인 가리기로 단정한 인상\n\n가일컷은 헤어라인을 가려주어 보다 단정한 느낌을 줄 수 있습니다. 이는 외모의 세련됨을 더하고, 자칫 불규칙해 보일 수 있는 부분을 보완하여 깔끔한 이미지를 원하는 고객에게 특히 유용합니다.",
    "report_json": {
      "title": "가일컷 중심 헤어스타일 커뮤니티",
      "summary": "이 커뮤니티는 가일컷을 중심으로 다양한 헤어스타일과 특징들이 조화를 이루며, 스타일링과 관리의 용이성을 강조합니다. 가일컷은 여러 머리 특징과 조화를 이루어 성숙하고 깔끔한 이미지를 만들어낼 수 있는 스타일입니다.",
      "rating": 8.5,
      "rating_explanation": "가일컷은 다양한 얼굴형과 모발 특성에 잘 어울리며, 관리가 용이하다는 점에서 높은 점수를 부여했습니다.",
      "findings": [
        {
          "summary": "가일컷과 굵은 모발의 조화",
          "explanation": "가일컷은 굵은 모발에 잘 어울리는 스타일로, 두껍고 힘있는 머리카락의 장점을 살려줍니다. 이 스타일은 자연스러운 헤어라인을 형성하여 시원한 느낌을 강화시키며, 깔끔하게 정돈된 인상을 줄 수 있습니다."
        },
        {
          "summary": "가일컷의 다운펌 시너지",
          "explanation": "가일컷은 다운펌과 함께 시술될 때 더욱 깔끔한 댄디 스타일로 연출됩니다. 다운펌은 머리카락의 뿌리를 눌러 부드럽고 자연스러운 스타일을 만들어 주는데, 이 결합으로 인해 더욱 정돈된 느낌을 얻을 수 있습니다."
        },
        {
          "summary": "리프팅 효과로 얼굴형 보완",
          "explanation": "가일컷은 리프팅 효과를 통해 머리의 볼륨감을 높이며, 동시에 얼굴형을 보완하는 특징을 가지고 있습니다. 이로 인해 고객들은 더욱 균형 잡힌 얼굴형을 연출할 수 있으며, 세련된 인상을 심어줄 수 있습니다."
        },
        {
          "summary": "성숙하고 깔끔한 이미지 제공",
          "explanation": "가일컷은 성숙하고 깔끔한 분위기를 주는 스타일 특징이 있어, 사회적이나 직장에서의 분위기를 고려할 때 유용한 선택이 됩니다. 이 스타일은 다양한 연령층에 걸쳐 선호되며, 정돈된 인상이 주요 요구사항인 경우 좋습니다."
        },
        {
          "summary": "쉽게 관리할 수 있는 스타일",
          "explanation": "가일컷은 관리와 스타일링이 용이하다는 장점이 있어 바쁜 현대인들에게 특히 추천할 수 있습니다. 빠르게 스타일을 잡을 수 있고, 일상적인 손질이 덜 필요하다는 점에서 많은 소비자에게 인기를 끌고 있습니다."
        },
        {
          "summary": "다양한 앞머리 길이 조절",
          "explanation": "가일컷은 앞머리의 길이를 조절하여 여러 가지 이미지를 연출할 수 있는 유연성을 제공합니다. 고객의 얼굴형이나 스타일에 따라 길이를 조절하여 맞춤형 스타일링이 가능하며, 다양한 분위기를 시도할 수 있습니다."
        },
        {
          "summary": "이마가 넓은 얼굴형에 적합",
          "explanation": "가일컷은 이마가 넓은 얼굴형에 적합하도록 설계되어 있습니다. 앞머리의 길이를 조절하여 넓은 이마를 부분적으로 가림으로써 전체적인 균형을 잡아 주는 효과가 있습니다."
        },
        {
          "summary": "프론트 오픈으로 시원한 느낌 강조",
          "explanation": "가일컷은 이마를 드러내는 프론트 오픈 스타일을 특징으로 하여 시원한 느낌을 강조합니다. 이는 특히 더운 날씨에 적합하며, 여름철에 인기 있는 스타일로 자리매김하고 있습니다."
        },
        {
          "summary": "헤어라인 가리기로 단정한 인상",
          "explanation": "가일컷은 헤어라인을 가려주어 보다 단정한 느낌을 줄 수 있습니다. 이는 외모의 세련됨을 더하고, 자칫 불규칙해 보일 수 있는 부분을 보완하여 깔끔한 이미지를 원하는 고객에게 특히 유용합니다."
        }
      ]
    },
    "level": 1,
    "title": "Cluster 11",
    "edges": [
      [
        "\"가일컷\"",
        "\"필러스컷\""
      ],
      [
        "\"가일컷\"",
        "\"쉽게 관리할 수 있는 스타일\""
      ],
      [
        "\"가일컷\"",
        "\"프론트 오픈\""
      ],
      [
        "\"가일컷\"",
        "\"직모\""
      ],
      [
        "\"가일컷\"",
        "\"다운펌\""
      ],
      [
        "\"가일컷\"",
        "\"적당한 길이의 단발\""
      ],
      [
        "\"가일컷\"",
        "\"성숙하고 깔끔한 분위기\""
      ],
      [
        "\"가일컷\"",
        "\"이마가 넓은 얼굴형\""
      ],
      [
        "\"가일컷\"",
        "\"헤어라인 가리기\""
      ],
      [
        "\"가일컷\"",
        "\"앞머리 길이 조절\""
      ],
      [
        "\"가일컷\"",
        "\"리프팅 효과\""
      ],
      [
        "\"가일컷\"",
        "\"굵은 모발\""
      ]
    ],
    "nodes": [
      "\"앞머리 길이 조절\"",
      "\"적당한 길이의 단발\"",
      "\"다운펌\"",
      "\"리프팅 효과\"",
      "\"쉽게 관리할 수 있는 스타일\"",
      "\"헤어라인 가리기\"",
      "\"프론트 오픈\"",
      "\"성숙하고 깔끔한 분위기\"",
      "\"이마가 넓은 얼굴형\"",
      "\"굵은 모발\"",
      "\"가일컷\""
    ],
    "chunk_ids": [
      "chunk-aa3286f7d8b8f5afc0b3db44ded13e3f",
      "chunk-6537c051bb955b20213bcfacafe0ae23"
    ],
    "occurrence": 0.5,
    "sub_communities": []
  },
  "16": {
    "report_string": "# 히피펌과 가는 모발 스타일 커뮤니티\n\n이 헤어스타일 커뮤니티는 히피펌을 중심으로 가는 모발과 그러한 특징을 가진 다양한 스타일을 아우릅니다. 개성적이고 젊은 이미지를 지향하며, 특정 헤어 조건에 잘 맞는 스타일들이 추천됩니다.\n\n## 히피펌과 가는 모발의 조화\n\n히피펌은 가는 모발의 고객에게 자연스러운 컬을 제공하여 풍성한 스타일로 연출되도록 돕습니다. 이는 가벼운 머리카락을 가진 사람들에게 이상적인 선택이 될 수 있습니다.\n\n## 히피펌의 관리 난이도\n\n히피펌은 그 자체로 웨이브가 많아 유지 관리가 까다롭다는 점에서 고객의 스타일링 노력을 요합니다. 이 정보를 전달하여 고객에게 현실적인 기대치를 제공합니다.\n\n## 스핀스왈로펌과 부드러운 느낌\n\n스핀스왈로펌은 가는 모발에 적합하며 부드러운 컬을 강조한다는 점에서 고객들에게 추천할 만한 스타일입니다. 이는 젊고 신선한 이미지 연출에 기여할 수 있습니다.\n\n## 광대가 발달한 얼굴형에 적합한 스타일\n\n히피펌 스타일은 광대가 발달한 얼굴형의 고객에게도 잘 어울린다고 알려져 있으며, 이 특성은 다양한 얼굴형 고객을 위한 스타일링 옵션을 확대합니다.\n\n## 젊고 개성적인 스타일 선호\n\n히피펌의 널리 알리는 특성 중 하나는 젊고 개성적인 스타일을 원하는 고객에게 추천된다는 것입니다. 이는 젊은 층의 스타일 아이콘으로 자리잡는 데 기여하고 있습니다.",
    "report_json": {
      "title": "히피펌과 가는 모발 스타일 커뮤니티",
      "summary": "이 헤어스타일 커뮤니티는 히피펌을 중심으로 가는 모발과 그러한 특징을 가진 다양한 스타일을 아우릅니다. 개성적이고 젊은 이미지를 지향하며, 특정 헤어 조건에 잘 맞는 스타일들이 추천됩니다.",
      "rating": 6.5,
      "rating_explanation": "히피펌은 개성과 트렌드를 강조하며 특정 면에서 인기를 끌지만, 관리의 까다로움이 있어 추천 횟수가 제한적입니다.",
      "findings": [
        {
          "summary": "히피펌과 가는 모발의 조화",
          "explanation": "히피펌은 가는 모발의 고객에게 자연스러운 컬을 제공하여 풍성한 스타일로 연출되도록 돕습니다. 이는 가벼운 머리카락을 가진 사람들에게 이상적인 선택이 될 수 있습니다."
        },
        {
          "summary": "히피펌의 관리 난이도",
          "explanation": "히피펌은 그 자체로 웨이브가 많아 유지 관리가 까다롭다는 점에서 고객의 스타일링 노력을 요합니다. 이 정보를 전달하여 고객에게 현실적인 기대치를 제공합니다."
        },
        {
          "summary": "스핀스왈로펌과 부드러운 느낌",
          "explanation": "스핀스왈로펌은 가는 모발에 적합하며 부드러운 컬을 강조한다는 점에서 고객들에게 추천할 만한 스타일입니다. 이는 젊고 신선한 이미지 연출에 기여할 수 있습니다."
        },
        {
          "summary": "광대가 발달한 얼굴형에 적합한 스타일",
          "explanation": "히피펌 스타일은 광대가 발달한 얼굴형의 고객에게도 잘 어울린다고 알려져 있으며, 이 특성은 다양한 얼굴형 고객을 위한 스타일링 옵션을 확대합니다."
        },
        {
          "summary": "젊고 개성적인 스타일 선호",
          "explanation": "히피펌의 널리 알리는 특성 중 하나는 젊고 개성적인 스타일을 원하는 고객에게 추천된다는 것입니다. 이는 젊은 층의 스타일 아이콘으로 자리잡는 데 기여하고 있습니다."
        }
      ]
    },
    "level": 1,
    "title": "Cluster 16",
    "edges": [
      [
        "\"가는 모발\"",
        "\"스핀스왈로펌\""
      ],
      [
        "\"관리의 까다로움\"",
        "\"히피펌\""
      ],
      [
        "\"부드러운 느낌\"",
        "\"스핀스왈로펌\""
      ],
      [
        "\"젊고 개성적인 스타일\"",
        "\"히피펌\""
      ],
      [
        "\"가는 모발\"",
        "\"히피펌\""
      ],
      [
        "\"광대가 발달한 얼굴형\"",
        "\"히피펌\""
      ],
      [
        "\"가는 모발\"",
        "\"가르마펌\""
      ]
    ],
    "nodes": [
      "\"가는 모발\"",
      "\"광대가 발달한 얼굴형\"",
      "\"관리의 까다로움\"",
      "\"스핀스왈로펌\"",
      "\"젊고 개성적인 스타일\"",
      "\"히피펌\""
    ],
    "chunk_ids": [
      "chunk-26f0ef8ea2f7ad3255c67cac5e87a11a",
      "chunk-6537c051bb955b20213bcfacafe0ae23"
    ],
    "occurrence": 0.5,
    "sub_communities": []
  },
  "12": {
    "report_string": "# 필러스컷 및 관리 용이한 스타일 커뮤니티\n\n이 커뮤니티는 필러스컷과 관리 용이한 스타일을 중심으로 한 다양한 헤어스타일 조합으로 구성되어 있으며, 특히 유지 및 스타일링이 간편한 특성이 강조됩니다. 필러스컷은 가일컷과의 조합을 통해 다양한 분위기를 연출할 수 있습니다.\n\n## 필러스컷과 가일컷의 다양한 스타일링 가능성\n\n필러스컷은 가일컷과 함께 사용될 때 스타일링 방법에 따라 다른 분위기를 연출할 수 있는 특성이 있습니다. 이는 고객들에게 맞춤형 스타일링 옵션을 제공하여 소비자의 선택의 폭을 넓히는 데 기여합니다.\n\n## 관리 용이한 스타일로서의 필러스컷의 인기\n\n필러스컷은 유지 및 스타일링이 간편하여 많은 사람들에게 인기를 끌고 있습니다. 특히 바쁜 일상 속에서 손 easily 다룰 수 있는 스타일을 찾는 고객들에게 많은 추천을 받고 있습니다.",
    "report_json": {
      "title": "필러스컷 및 관리 용이한 스타일 커뮤니티",
      "summary": "이 커뮤니티는 필러스컷과 관리 용이한 스타일을 중심으로 한 다양한 헤어스타일 조합으로 구성되어 있으며, 특히 유지 및 스타일링이 간편한 특성이 강조됩니다. 필러스컷은 가일컷과의 조합을 통해 다양한 분위기를 연출할 수 있습니다.",
      "rating": 6.0,
      "rating_explanation": "관리 용이성과 스타일링의 다양성을 제공하는 헤어스타일이므로 다수의 사용자에게 적합하며, 상대적으로 활용도가 높아 중간 수준의 점수를 부여했습니다.",
      "findings": [
        {
          "summary": "필러스컷과 가일컷의 다양한 스타일링 가능성",
          "explanation": "필러스컷은 가일컷과 함께 사용될 때 스타일링 방법에 따라 다른 분위기를 연출할 수 있는 특성이 있습니다. 이는 고객들에게 맞춤형 스타일링 옵션을 제공하여 소비자의 선택의 폭을 넓히는 데 기여합니다."
        },
        {
          "summary": "관리 용이한 스타일로서의 필러스컷의 인기",
          "explanation": "필러스컷은 유지 및 스타일링이 간편하여 많은 사람들에게 인기를 끌고 있습니다. 특히 바쁜 일상 속에서 손 easily 다룰 수 있는 스타일을 찾는 고객들에게 많은 추천을 받고 있습니다."
        }
      ]
    },
    "level": 1,
    "title": "Cluster 12",
    "edges": [
      [
        "\"가일컷\"",
        "\"필러스컷\""
      ],
      [
        "\"관리 용이한 스타일\"",
        "\"필러스컷\""
      ]
    ],
    "nodes": [
      "\"필러스컷\"",
      "\"관리 용이한 스타일\""
    ],
    "chunk_ids": [
      "chunk-aa3286f7d8b8f5afc0b3db44ded13e3f"
    ],
    "occurrence": 0.25,
    "sub_communities": []
  },
  "17": {
    "report_string": "# 가일 포마드펌 스타일 커뮤니티\n\n이 커뮤니티는 가일 포마드펌을 중심으로 구성된 다양한 스타일 요소로 이루어져 있으며, 이 스타일은 특징적으로 도시적인 이미지를 제공합니다. 볼륨감 있는 웨이브와 짧은 앞머리와의 조화로 스타일의 완성도를 높이고, 트렌디한 느낌을 강화합니다.\n\n## 가일 포마드펌과 볼륨감 있는 웨이브의 조화\n\n가일 포마드펌은 볼륨감 있는 웨이브를 갖춘 스타일로, 이 두 요소가 결합하여 더욱 도시적이고 세련된 이미지를 연출합니다. 볼륨감 있는 웨이브는 스타일에 생동감을 추가하며, 다양한 상황에 어울리는 유연성을 제공합니다.\n\n## 가일 포마드펌과 짧은 앞머리의 균형\n\n가일 포마드펌은 짧은 앞머리 스타일과 완벽하게 어우러져 깔끔하면서도 세련된 이미지를 만들어냅니다. 이러한 조합은 얼굴형 보완과 동시에 다양한 연령대에 적합한 스타일을 제공합니다.\n\n## 가일 포마드펌과 포마드펌의 연관성\n\n가일 포마드펌은 포마드펌과 스타일적으로 연결되어 있어, 둘은 종종 함께 추천됩니다. 포마드펌의 전통적인 매력을 현대적인 도시 이미지로 변형하여 활용할 수 있습니다.\n\n## 도시적인 느낌의 스타일 선호\n\n가일 포마드펌은 도시적인 느낌을 강조하여 대도시 거주자들 사이에서 인기를 끌고 있습니다. 이는 현대 사회에서 가볍고 편안한 스타일을 선호하는 트렌드의 반영입니다.",
    "report_json": {
      "title": "가일 포마드펌 스타일 커뮤니티",
      "summary": "이 커뮤니티는 가일 포마드펌을 중심으로 구성된 다양한 스타일 요소로 이루어져 있으며, 이 스타일은 특징적으로 도시적인 이미지를 제공합니다. 볼륨감 있는 웨이브와 짧은 앞머리와의 조화로 스타일의 완성도를 높이고, 트렌디한 느낌을 강화합니다.",
      "rating": 7.5,
      "rating_explanation": "도시적인 이미지와 트렌드를 반영한 스타일 조합이 인기를 끌고 있어 신뢰성과 추천도가 높습니다.",
      "findings": [
        {
          "summary": "가일 포마드펌과 볼륨감 있는 웨이브의 조화",
          "explanation": "가일 포마드펌은 볼륨감 있는 웨이브를 갖춘 스타일로, 이 두 요소가 결합하여 더욱 도시적이고 세련된 이미지를 연출합니다. 볼륨감 있는 웨이브는 스타일에 생동감을 추가하며, 다양한 상황에 어울리는 유연성을 제공합니다."
        },
        {
          "summary": "가일 포마드펌과 짧은 앞머리의 균형",
          "explanation": "가일 포마드펌은 짧은 앞머리 스타일과 완벽하게 어우러져 깔끔하면서도 세련된 이미지를 만들어냅니다. 이러한 조합은 얼굴형 보완과 동시에 다양한 연령대에 적합한 스타일을 제공합니다."
        },
        {
          "summary": "가일 포마드펌과 포마드펌의 연관성",
          "explanation": "가일 포마드펌은 포마드펌과 스타일적으로 연결되어 있어, 둘은 종종 함께 추천됩니다. 포마드펌의 전통적인 매력을 현대적인 도시 이미지로 변형하여 활용할 수 있습니다."
        },
        {
          "summary": "도시적인 느낌의 스타일 선호",
          "explanation": "가일 포마드펌은 도시적인 느낌을 강조하여 대도시 거주자들 사이에서 인기를 끌고 있습니다. 이는 현대 사회에서 가볍고 편안한 스타일을 선호하는 트렌드의 반영입니다."
        }
      ]
    },
    "level": 1,
    "title": "Cluster 17",
    "edges": [
      [
        "\"가일 포마드펌\"",
        "\"포마드펌\""
      ],
      [
        "\"가일 포마드펌\"",
        "\"짧은 앞머리\""
      ],
      [
        "\"가일 포마드펌\"",
        "\"볼륨감 있는 웨이브\""
      ]
    ],
    "nodes": [
      "\"가일 포마드펌\"",
      "\"볼륨감 있는 웨이브\"",
      "\"짧은 앞머리\""
    ],
    "chunk_ids": [
      "chunk-26f0ef8ea2f7ad3255c67cac5e87a11a"
    ],
    "occurrence": 0.25,
    "sub_communities": []
  },
  "1": {
    "report_string": "# 태슬 컷과 스타일 커뮤니티\n\n이 커뮤니티는 태슬 컷을 중심으로 다양한 특징을 지닌 헤어 스타일 및 그에 관련된 인물들이 조화를 이루고 있습니다. 태슬 컷은 세련된 느낌과 발랄한 이미지를 동시에 강조하는 스타일로, 여러 얼굴형에 어울립니다. 김나영과 윈터와 같은 유명 인사들도 이 스타일을 채택하여 새로운 트렌드를 이끌고 있습니다.\n\n## 태슬 컷의 다재다능함\n\n태슬 컷은 짧고 깔끔한 라인에 텍스처 처리된 끝부분으로, 발랄하면서도 세련된 이미지를 줄 수 있는 매우 적응력이 뛰어난 스타일입니다. 이 스타일은 다양한 얼굴형에 적합하며, 특히 계란형 얼굴과 잘 어울리는 것으로 알려져 있습니다.\n\n## 김나영과 태슬 컷 연결 고리\n\n한국의 유명한 연예인 김나영은 태슬 컷 헤어스타일을 통해 많은 관심을 받고 있으며, 그녀의 선택은 이 스타일에 대한 인지도를 높였습니다. 이러한 유명 인사의 선택은 대중의 스타일 선택에 큰 영향을 미치며, 태슬 컷의 인기 상승에 기여하고 있습니다.\n\n## 윈터의 변신과 태슬 컷\n\n아이돌 그룹의 멤버인 윈터는 태슬 컷으로의 변신을 통해 신선한 이미지를 선보였습니다. 이처럼 인기 있는 인물이 새로운 스타일을 채택함에 따라 많은 팬들이 이 스타일을 따라 하게 되며, 태슬 컷의 대중적인 수용도를 높이는 효과가 있습니다.\n\n## 태슬 컷의 최신 트렌드 반영\n\n태슬 컷은 '새해 변신'과 같은 테마에 잘 맞아, 새해를 맞아 새로운 변화 중 하나로 추천되고 있습니다. 많은 사람들이 새해에는 새로운 스타일을 시도하고자 하므로, 태슬 컷은 이러한 욕구를 충족시키는 완벽한 선택이 될 수 있습니다.\n\n## 태슬 컷과 다른 스타일의 비교\n\n태슬 컷은 칼 단발과 비교할 때 발랄하고 세련된 느낌을 주며, 각진 얼굴형에도 잘 어울리는 특성을 지니고 있습니다. 이러한 특성 덕분에 다양한 얼굴형에 적응할 수 있는 가능성이 커지며, 스타일링의 폭이 넓어집니다.",
    "report_json": {
      "title": "태슬 컷과 스타일 커뮤니티",
      "summary": "이 커뮤니티는 태슬 컷을 중심으로 다양한 특징을 지닌 헤어 스타일 및 그에 관련된 인물들이 조화를 이루고 있습니다. 태슬 컷은 세련된 느낌과 발랄한 이미지를 동시에 강조하는 스타일로, 여러 얼굴형에 어울립니다. 김나영과 윈터와 같은 유명 인사들도 이 스타일을 채택하여 새로운 트렌드를 이끌고 있습니다.",
      "rating": 8.5,
      "rating_explanation": "태슬 컷은 인기 있는 인물들에 의해 주목받고 있으며, 다양한 이미지와 스타일을 연출할 수 있는 가능성이 높아 높은 점수를 부여했습니다.",
      "findings": [
        {
          "summary": "태슬 컷의 다재다능함",
          "explanation": "태슬 컷은 짧고 깔끔한 라인에 텍스처 처리된 끝부분으로, 발랄하면서도 세련된 이미지를 줄 수 있는 매우 적응력이 뛰어난 스타일입니다. 이 스타일은 다양한 얼굴형에 적합하며, 특히 계란형 얼굴과 잘 어울리는 것으로 알려져 있습니다."
        },
        {
          "summary": "김나영과 태슬 컷 연결 고리",
          "explanation": "한국의 유명한 연예인 김나영은 태슬 컷 헤어스타일을 통해 많은 관심을 받고 있으며, 그녀의 선택은 이 스타일에 대한 인지도를 높였습니다. 이러한 유명 인사의 선택은 대중의 스타일 선택에 큰 영향을 미치며, 태슬 컷의 인기 상승에 기여하고 있습니다."
        },
        {
          "summary": "윈터의 변신과 태슬 컷",
          "explanation": "아이돌 그룹의 멤버인 윈터는 태슬 컷으로의 변신을 통해 신선한 이미지를 선보였습니다. 이처럼 인기 있는 인물이 새로운 스타일을 채택함에 따라 많은 팬들이 이 스타일을 따라 하게 되며, 태슬 컷의 대중적인 수용도를 높이는 효과가 있습니다."
        },
        {
          "summary": "태슬 컷의 최신 트렌드 반영",
          "explanation": "태슬 컷은 '새해 변신'과 같은 테마에 잘 맞아, 새해를 맞아 새로운 변화 중 하나로 추천되고 있습니다. 많은 사람들이 새해에는 새로운 스타일을 시도하고자 하므로, 태슬 컷은 이러한 욕구를 충족시키는 완벽한 선택이 될 수 있습니다."
        },
        {
          "summary": "태슬 컷과 다른 스타일의 비교",
          "explanation": "태슬 컷은 칼 단발과 비교할 때 발랄하고 세련된 느낌을 주며, 각진 얼굴형에도 잘 어울리는 특성을 지니고 있습니다. 이러한 특성 덕분에 다양한 얼굴형에 적응할 수 있는 가능성이 커지며, 스타일링의 폭이 넓어집니다."
        }
      ]
    },
    "level": 0,
    "title": "Cluster 1",
    "edges": [
      [
        "\"계란형 얼굴\"",
        "\"태슬 컷\""
      ],
      [
        "\"레이어드컷 컬펌\"",
        "\"세련된 느낌\""
      ],
      [
        "\"둥근 얼굴형\"",
        "\"태슬 컷\""
      ],
      [
        "\"칼 단발\"",
        "\"태슬 컷\""
      ],
      [
        "\"세련된 느낌\"",
        "\"태슬 컷\""
      ],
      [
        "\"발랄한 느낌\"",
        "\"태슬 컷\""
      ],
      [
        "\"가르마펌\"",
        "\"계란형 얼굴\""
      ],
      [
        "\"각진 얼굴형\"",
        "\"태슬 컷\""
      ],
      [
        "\"윈터\"",
        "\"태슬 컷\""
      ],
      [
        "\"김나영\"",
        "\"태슬 컷\""
      ],
      [
        "\"요정 같은 이미지\"",
        "\"태슬 컷\""
      ],
      [
        "\"새해 변신\"",
        "\"태슬 컷\""
      ]
    ],
    "nodes": [
      "\"칼 단발\"",
      "\"윈터\"",
      "\"요정 같은 이미지\"",
      "\"세련된 느낌\"",
      "\"김나영\"",
      "\"발랄한 느낌\"",
      "\"계란형 얼굴\"",
      "\"태슬 컷\"",
      "\"새해 변신\""
    ],
    "chunk_ids": [
      "chunk-6c4423bbdfde7099b7dd10cf79466327",
      "chunk-c133af03a51e41eab158f1bb61816b50",
      "chunk-6537c051bb955b20213bcfacafe0ae23"
    ],
    "occurrence": 0.75,
    "sub_communities": []
  },
  "0": {
    "report_string": "# 가르마펌과 각진 얼굴형 스타일 커뮤니티\n\n이 커뮤니티는 가르마펌을 중심으로 각진 얼굴형에 잘 어울리는 다양한 스타일을 제안하는 그룹입니다. '가르마펌'은 남성 고객을 위한 스타일로, 세련된 인상과 다양한 얼굴형을 고려한 맞춤형 시술이 특징입니다.\n\n## 가르마펌의 다양한 얼굴형 적합성\n\n가르마펌은 각진 얼굴형, 계란형 얼굴 등 다양한 얼굴형에 잘 어울린다고 평가받으며, 이러한 특성으로 인해 특정 이벤트나 상황에 적합한 스타일로 인식됩니다. 특히 각진 얼굴형에 대해서는 부드러운 인상을 주는 특성 덕분에 수요가 높습니다.\n\n## 면접 및 소개팅 준비에 적합한 스타일\n\n가르마펌은 직장 인터뷰나 소개팅 등 사람들에게 좋은 첫인상을 주는 상황에서 신뢰감과 매력을 동시에 제공할 수 있는 스타일로 인식되고 있습니다. 이 스타일은 깔끔하고 세련된 인상을 주며, 구직 과정과 인간관계에서 긍정적인 효과를 갖출 수 있습니다.\n\n## 볼륨 부족 보완\n\n가르마펌은 볼륨이 부족한 머리카락에도 효과적으로 적용될 수 있으며, 이로 인해 고객들은 보다 풍성한 느낌을 경험할 수 있습니다. 특히, 얇고 가는 모발을 가진 이들에게는 유용한 선택이 될 수 있습니다.\n\n## 개인 맞춤형 시술 강조\n\n가르마펌은 개인 맞춤형 시술로서 각 개인의 얼굴형과 모발 특성에 맞춰 스타일링이 가능하다는 점에서 주목받고 있습니다. 이러한 맞춤형 접근은 고객의 만족도를 높이며, 스타일의 다양성을 더합니다.\n\n## 가르마펌과 다른 스타일 간의 조화\n\n가르마펌은 쉐도우펌 등 다른 스타일과 조화를 이루며, 고객들은 이러한 조합을 통해 다양한 분위기를 연출할 수 있습니다. 여러 스타일을 함께 제안함으로써 스타일링의 가능성을 넓혀줍니다.\n\n## 장발 및 중간 길이 단발과의 조화\n\n가르마펌은 장발 및 중간 길이 단발 등 다양한 길이의 머리카락에서도 잘 어울립니다. 이러한 응용은 고객들이 더 많은 스타일 선택지를 가지게 해줍니다. 길이에 따라 시술 가능성이 다르며, 고객에게 더욱 폭넓은 옵션을 제공합니다.",
    "report_json": {
      "title": "가르마펌과 각진 얼굴형 스타일 커뮤니티",
      "summary": "이 커뮤니티는 가르마펌을 중심으로 각진 얼굴형에 잘 어울리는 다양한 스타일을 제안하는 그룹입니다. '가르마펌'은 남성 고객을 위한 스타일로, 세련된 인상과 다양한 얼굴형을 고려한 맞춤형 시술이 특징입니다.",
      "rating": 8.5,
      "rating_explanation": "가르마펌은 다양한 모발 성질과 얼굴형에 잘 어울리며, 특히 면접이나 소개팅 등 중요한 자리에서의 스타일링에 적합하여 매우 높은 추천 점수를 부여했습니다.",
      "findings": [
        {
          "summary": "가르마펌의 다양한 얼굴형 적합성",
          "explanation": "가르마펌은 각진 얼굴형, 계란형 얼굴 등 다양한 얼굴형에 잘 어울린다고 평가받으며, 이러한 특성으로 인해 특정 이벤트나 상황에 적합한 스타일로 인식됩니다. 특히 각진 얼굴형에 대해서는 부드러운 인상을 주는 특성 덕분에 수요가 높습니다."
        },
        {
          "summary": "면접 및 소개팅 준비에 적합한 스타일",
          "explanation": "가르마펌은 직장 인터뷰나 소개팅 등 사람들에게 좋은 첫인상을 주는 상황에서 신뢰감과 매력을 동시에 제공할 수 있는 스타일로 인식되고 있습니다. 이 스타일은 깔끔하고 세련된 인상을 주며, 구직 과정과 인간관계에서 긍정적인 효과를 갖출 수 있습니다."
        },
        {
          "summary": "볼륨 부족 보완",
          "explanation": "가르마펌은 볼륨이 부족한 머리카락에도 효과적으로 적용될 수 있으며, 이로 인해 고객들은 보다 풍성한 느낌을 경험할 수 있습니다. 특히, 얇고 가는 모발을 가진 이들에게는 유용한 선택이 될 수 있습니다."
        },
        {
          "summary": "개인 맞춤형 시술 강조",
          "explanation": "가르마펌은 개인 맞춤형 시술로서 각 개인의 얼굴형과 모발 특성에 맞춰 스타일링이 가능하다는 점에서 주목받고 있습니다. 이러한 맞춤형 접근은 고객의 만족도를 높이며, 스타일의 다양성을 더합니다."
        },
        {
          "summary": "가르마펌과 다른 스타일 간의 조화",
          "explanation": "가르마펌은 쉐도우펌 등 다른 스타일과 조화를 이루며, 고객들은 이러한 조합을 통해 다양한 분위기를 연출할 수 있습니다. 여러 스타일을 함께 제안함으로써 스타일링의 가능성을 넓혀줍니다."
        },
        {
          "summary": "장발 및 중간 길이 단발과의 조화",
          "explanation": "가르마펌은 장발 및 중간 길이 단발 등 다양한 길이의 머리카락에서도 잘 어울립니다. 이러한 응용은 고객들이 더 많은 스타일 선택지를 가지게 해줍니다. 길이에 따라 시술 가능성이 다르며, 고객에게 더욱 폭넓은 옵션을 제공합니다."
        }
      ]
    },
    "level": 0,
    "title": "Cluster 0",
    "edges": [
      [
        "\"각진 얼굴형\"",
        "\"애즈펌\""
      ],
      [
        "\"가르마펌\"",
        "\"소개팅 준비\""
      ],
      [
        "\"가르마펌\"",
        "\"개인 맞춤형 시술\""
      ],
      [
        "\"가르마펌\"",
        "\"중간 길이의 단발\""
      ],
      [
        "\"가르마펌\"",
        "\"내추럴 가르마펌\""
      ],
      [
        "\"가르마펌\"",
        "\"곱슬 모발\""
      ],
      [
        "\"가르마펌\"",
        "\"계란형 얼굴\""
      ],
      [
        "\"가르마펌\"",
        "\"직모\""
      ],
      [
        "\"가르마펌\"",
        "\"면접 준비\""
      ],
      [
        "\"각진 얼굴형\"",
        "\"태슬 컷\""
      ],
      [
        "\"가르마펌\"",
        "\"볼륨이 부족한 경우\""
      ],
      [
        "\"가는 모발\"",
        "\"가르마펌\""
      ],
      [
        "\"가르마펌\"",
        "\"세련된 인상\""
      ],
      [
        "\"가르마펌\"",
        "\"각진 얼굴형\""
      ],
      [
        "\"가르마펌\"",
        "\"장발\""
      ],
      [
        "\"가르마펌\"",
        "\"쉐도우펌\""
      ]
    ],
    "nodes": [
      "\"애즈펌\"",
      "\"곱슬 모발\"",
      "\"내추럴 가르마펌\"",
      "\"중간 길이의 단발\"",
      "\"볼륨이 부족한 경우\"",
      "\"가르마펌\"",
      "\"면접 준비\"",
      "\"쉐도우펌\"",
      "\"세련된 인상\"",
      "\"소개팅 준비\"",
      "\"장발\"",
      "\"각진 얼굴형\"",
      "\"개인 맞춤형 시술\""
    ],
    "chunk_ids": [
      "chunk-6c4423bbdfde7099b7dd10cf79466327",
      "chunk-6537c051bb955b20213bcfacafe0ae23"
    ],
    "occurrence": 0.5,
    "sub_communities": [
      "9",
      "10"
    ]
  },
  "4": {
    "report_string": "# 레이어드펌 및 중간머리 굵은 컬펌 스타일 커뮤니티\n\n이 커뮤니티는 레이어드펌과 중간머리 굵은 컬펌을 중심으로 한 다양한 헤어스타일 요소들이 조합되어 구성된 그룹입니다. 다양한 얼굴형에 적합한 스타일을 제공하며, 자연스럽고 부드러운 느낌을 강조하는 것이 특징입니다.\n\n## 레이어드펌의 볼륨감 강조\n\n레이어드펌은 자연스러운 부드러운 웨이브를 강조하여 볼륨감을 극대화합니다. 이 스타일은 얇은 모발에 특히 적합하며, 사용자가 자신감 있는 이미지를 연출할 수 있도록 돕습니다. 가벼운 레이어드가 들어간 이 스타일은 시술 후 일상에서 유지하는 데 용이합니다.\n\n## 중간머리 굵은 컬펌의 유연성\n\n중간머리 굵은 컬펌은 쇄골 위까지의 중간 길이에서 자연스럽고 관리하기 쉬운 분위기를 연출합니다. 이 스타일은 다양한 길이와 모발 유형에 맞춰 조정될 수 있어, 고객의 개성과 취향에 따라 스타일링의 유연성을 제공합니다.\n\n## 두 얼굴형에 적합한 스타일 추천\n\n예를 들어, 레이어드펌은 긴 얼굴형에 볼륨감을 추가하여 부드러운 인상을 제공하는 반면, 둥근 얼굴형에는 중간머리 굵은 컬펌이 더욱 어울리며 갸름해 보이는 효과를 줄 수 있습니다. 다양한 얼굴형에 맞는 스타일 조합을 통해 개인화된 추천이 가능하다는 점이 이 커뮤니티의 강점입니다.\n\n## 얇은 모발의 최적화된 솔루션\n\n레이어드펌과 중간머리 굵은 컬펌은 모두 얇은 모발에 볼륨을 주는 효과가 있습니다. 고객은 이 스타일을 통해 모발이 풍성하게 보이는 이점을 경험할 수 있으며, 이는 특히 스타일이 더욱 매력적으로 보이도록 합니다.\n\n## 깔끔하고 편안한 스타일링\n\n중간머리 굵은 컬펌은 깔끔하고 편안한 느낌을 제공하여 자주 스타일링하는 보다 간편한 솔루션을 제공합니다. 이는 바쁜 일상 속에서도 손쉽게 관리할 수 있도록 해주어 많은 고객이 선호하는 이유 중 하나입니다.\n\n## 자연스러운 웨이브 연출의 인기\n\n겹겹이 레이어링과 함께 중단발은 자연스러운 웨이브 연출에 효과적입니다. 고객들은 이 조합을 통해 더욱 세련되고 트렌디한 이미지를 유지할 수 있으며, 이는 현재 유행하는 스타일의 일환으로 자리잡고 있습니다.",
    "report_json": {
      "title": "레이어드펌 및 중간머리 굵은 컬펌 스타일 커뮤니티",
      "summary": "이 커뮤니티는 레이어드펌과 중간머리 굵은 컬펌을 중심으로 한 다양한 헤어스타일 요소들이 조합되어 구성된 그룹입니다. 다양한 얼굴형에 적합한 스타일을 제공하며, 자연스럽고 부드러운 느낌을 강조하는 것이 특징입니다.",
      "rating": 8.5,
      "rating_explanation": "이 커뮤니티 내의 스타일들이 다양하게 조합될 수 있으며, 각기 다른 얼굴형과 모발 유형에 적합하여 높은 인기도와 활용성을 가지고 있습니다.",
      "findings": [
        {
          "summary": "레이어드펌의 볼륨감 강조",
          "explanation": "레이어드펌은 자연스러운 부드러운 웨이브를 강조하여 볼륨감을 극대화합니다. 이 스타일은 얇은 모발에 특히 적합하며, 사용자가 자신감 있는 이미지를 연출할 수 있도록 돕습니다. 가벼운 레이어드가 들어간 이 스타일은 시술 후 일상에서 유지하는 데 용이합니다."
        },
        {
          "summary": "중간머리 굵은 컬펌의 유연성",
          "explanation": "중간머리 굵은 컬펌은 쇄골 위까지의 중간 길이에서 자연스럽고 관리하기 쉬운 분위기를 연출합니다. 이 스타일은 다양한 길이와 모발 유형에 맞춰 조정될 수 있어, 고객의 개성과 취향에 따라 스타일링의 유연성을 제공합니다."
        },
        {
          "summary": "두 얼굴형에 적합한 스타일 추천",
          "explanation": "예를 들어, 레이어드펌은 긴 얼굴형에 볼륨감을 추가하여 부드러운 인상을 제공하는 반면, 둥근 얼굴형에는 중간머리 굵은 컬펌이 더욱 어울리며 갸름해 보이는 효과를 줄 수 있습니다. 다양한 얼굴형에 맞는 스타일 조합을 통해 개인화된 추천이 가능하다는 점이 이 커뮤니티의 강점입니다."
        },
        {
          "summary": "얇은 모발의 최적화된 솔루션",
          "explanation": "레이어드펌과 중간머리 굵은 컬펌은 모두 얇은 모발에 볼륨을 주는 효과가 있습니다. 고객은 이 스타일을 통해 모발이 풍성하게 보이는 이점을 경험할 수 있으며, 이는 특히 스타일이 더욱 매력적으로 보이도록 합니다."
        },
        {
          "summary": "깔끔하고 편안한 스타일링",
          "explanation": "중간머리 굵은 컬펌은 깔끔하고 편안한 느낌을 제공하여 자주 스타일링하는 보다 간편한 솔루션을 제공합니다. 이는 바쁜 일상 속에서도 손쉽게 관리할 수 있도록 해주어 많은 고객이 선호하는 이유 중 하나입니다."
        },
        {
          "summary": "자연스러운 웨이브 연출의 인기",
          "explanation": "겹겹이 레이어링과 함께 중단발은 자연스러운 웨이브 연출에 효과적입니다. 고객들은 이 조합을 통해 더욱 세련되고 트렌디한 이미지를 유지할 수 있으며, 이는 현재 유행하는 스타일의 일환으로 자리잡고 있습니다."
        }
      ]
    },
    "level": 0,
    "title": "Cluster 4",
    "edges": [
      [
        "\"긴 얼굴형\"",
        "\"레이어드펌\""
      ],
      [
        "\"동안 효과\"",
        "\"레이어드펌\""
      ],
      [
        "\"둥근 얼굴형\"",
        "\"태슬 컷\""
      ],
      [
        "\"가벼운 웨이브\"",
        "\"중단발\""
      ],
      [
        "\"레이어드펌\"",
        "\"중간머리 굵은 컬펌\""
      ],
      [
        "\"중간머리 굵은 컬펌\"",
        "\"중단발\""
      ],
      [
        "\"깔끔하고 편안한 느낌\"",
        "\"중간머리 굵은 컬펌\""
      ],
      [
        "\"레이어드펌\"",
        "\"얇은 모발\""
      ],
      [
        "\"가슴 길이\"",
        "\"중간머리 굵은 컬펌\""
      ],
      [
        "\"얇은 모발\"",
        "\"중간머리 굵은 컬펌\""
      ],
      [
        "\"둥근 얼굴형\"",
        "\"부드러운 웨이브\""
      ],
      [
        "\"겹겹이 레이어링\"",
        "\"중단발\""
      ],
      [
        "\"레이어드펌\"",
        "\"부드러운 웨이브\""
      ]
    ],
    "nodes": [
      "\"중간머리 굵은 컬펌\"",
      "\"둥근 얼굴형\"",
      "\"가벼운 웨이브\"",
      "\"레이어드펌\"",
      "\"겹겹이 레이어링\"",
      "\"깔끔하고 편안한 느낌\"",
      "\"중단발\"",
      "\"부드러운 웨이브\"",
      "\"얇은 모발\"",
      "\"가슴 길이\""
    ],
    "chunk_ids": [
      "chunk-6c4423bbdfde7099b7dd10cf79466327",
      "chunk-3a88d84a6b27608aa907ee80770e479c",
      "chunk-66b882c32678c93fbdaac53754151003",
      "chunk-c133af03a51e41eab158f1bb61816b50"
    ],
    "occurrence": 1.0,
    "sub_communities": [
      "13",
      "14",
      "15"
    ]
  },
  "6": {
    "report_string": "# 겨울철 스타일과 로맨틱 분위기 헤어 커뮤니티\n\n이 커뮤니티는 겨울철에 적합한 헤어 스타일과 로맨틱한 요소를 강조하는 다양한 스타일과 액세서리를 중심으로 구성되어 있습니다. 플로럴 밴드와 애교머리 등은 특히 사랑스럽고 따뜻한 이미지를 연출하는 데 효과적입니다.\n\n## 겨울철 머리 정돈의 필요성\n\n겨울철 머리 정돈은 계절적 요인으로 인해 더욱 중요시되며, 헤어 스타일의 선택에 영향을 미칩니다. 겨울철은 추운 날씨로 인해 머리 관리가 어려울 수 있으므로 겨울철에 적합한 스타일이 요구됩니다.\n\n## 플로럴 밴드의 로맨틱한 특성\n\n플로럴 밴드는 로맨틱한 분위기를 강조하는 데 효과적이며, 다양한 스타일과 조화를 이룹니다. 특히 애교머리와 조합 시 더욱 사랑스러운 이미지를 연출할 수 있습니다.\n\n## 리프펌의 다양성과 적합성\n\n리프펌은 중성적이며 다양한 얼굴형에 어울리는 특징이 있어 많은 스타일 추천에서 포함됩니다. 이 스타일은 겨울철에 따뜻한 이미지를 주며 사랑스러운 분위기를 강조합니다.\n\n## 애교머리와 로맨틱한 곱슬\n\n애교머리는 둥글고 사랑스러운 이미지를 주는 스타일로, 플로럴 밴드와 함께 사용 시 더욱 풍부한 표현을 제공합니다. 이 조합은 특히 젊은 여성들에게 인기가 높습니다.\n\n## 사브리나 카펜터 스타일의 영향\n\n사브리나 카펜터의 스타일을 반영한 애교머리는 최근 미디어를 통해 더욱 주목받고 있습니다. 이는 젊은 소비자들 사이에서 트렌드로 자리잡고 있습니다.",
    "report_json": {
      "title": "겨울철 스타일과 로맨틱 분위기 헤어 커뮤니티",
      "summary": "이 커뮤니티는 겨울철에 적합한 헤어 스타일과 로맨틱한 요소를 강조하는 다양한 스타일과 액세서리를 중심으로 구성되어 있습니다. 플로럴 밴드와 애교머리 등은 특히 사랑스럽고 따뜻한 이미지를 연출하는 데 효과적입니다.",
      "rating": 8.0,
      "rating_explanation": "겨울철 헤어 스타일과 로맨틱한 분위기를 함께 담고 있어 트렌디하며, 다양한 스타일 조합이 가능해 인기가 높습니다.",
      "findings": [
        {
          "summary": "겨울철 머리 정돈의 필요성",
          "explanation": "겨울철 머리 정돈은 계절적 요인으로 인해 더욱 중요시되며, 헤어 스타일의 선택에 영향을 미칩니다. 겨울철은 추운 날씨로 인해 머리 관리가 어려울 수 있으므로 겨울철에 적합한 스타일이 요구됩니다."
        },
        {
          "summary": "플로럴 밴드의 로맨틱한 특성",
          "explanation": "플로럴 밴드는 로맨틱한 분위기를 강조하는 데 효과적이며, 다양한 스타일과 조화를 이룹니다. 특히 애교머리와 조합 시 더욱 사랑스러운 이미지를 연출할 수 있습니다."
        },
        {
          "summary": "리프펌의 다양성과 적합성",
          "explanation": "리프펌은 중성적이며 다양한 얼굴형에 어울리는 특징이 있어 많은 스타일 추천에서 포함됩니다. 이 스타일은 겨울철에 따뜻한 이미지를 주며 사랑스러운 분위기를 강조합니다."
        },
        {
          "summary": "애교머리와 로맨틱한 곱슬",
          "explanation": "애교머리는 둥글고 사랑스러운 이미지를 주는 스타일로, 플로럴 밴드와 함께 사용 시 더욱 풍부한 표현을 제공합니다. 이 조합은 특히 젊은 여성들에게 인기가 높습니다."
        },
        {
          "summary": "사브리나 카펜터 스타일의 영향",
          "explanation": "사브리나 카펜터의 스타일을 반영한 애교머리는 최근 미디어를 통해 더욱 주목받고 있습니다. 이는 젊은 소비자들 사이에서 트렌드로 자리잡고 있습니다."
        }
      ]
    },
    "level": 0,
    "title": "Cluster 6",
    "edges": [
      [
        "\"로맨틱한 분위기\"",
        "\"빅사이즈 리본 머리띠\""
      ],
      [
        "\"겨울철 머리 정돈\"",
        "\"두상\""
      ],
      [
        "\"긴 얼굴형\"",
        "\"리프펌\""
      ],
      [
        "\"애교머리\"",
        "\"플로럴 밴드\""
      ],
      [
        "\"겨울철 머리 정돈\"",
        "\"오버사이즈 리본 머리띠\""
      ],
      [
        "\"사브리나 카펜터 스타일\"",
        "\"애교머리\""
      ],
      [
        "\"로맨틱한 분위기\"",
        "\"플로럴 밴드\""
      ],
      [
        "\"겨울철 머리 정돈\"",
        "\"플로럴 밴드\""
      ],
      [
        "\"로맨틱한 분위기\"",
        "\"리프펌\""
      ]
    ],
    "nodes": [
      "\"사브리나 카펜터 스타일\"",
      "\"리프펌\"",
      "\"겨울철 머리 정돈\"",
      "\"로맨틱한 분위기\"",
      "\"애교머리\"",
      "\"플로럴 밴드\"",
      "\"오버사이즈 리본 머리띠\"",
      "\"두상\"",
      "\"빅사이즈 리본 머리띠\""
    ],
    "chunk_ids": [
      "chunk-37a74f6573f02895104dee3620b923fa",
      "chunk-26f0ef8ea2f7ad3255c67cac5e87a11a"
    ],
    "occurrence": 0.5,
    "sub_communities": []
  },
  "8": {
    "report_string": "# 레이어드컷 컬펌 스타일 커뮤니티\n\n이 커뮤니티는 레이어드컷 컬펌을 중심으로 다양한 헤어 스타일 요소와 관리 방법을 포함하고 있으며, 여성들 사이에서의 인기와 세련됨을 강조합니다. 이 스타일은 모발 손상을 최소화하고 자연스러운 컬을 연출할 수 있는 특징을 가지고 있어 바쁜 일상 속에서도 손쉽게 활용할 수 있습니다.\n\n## 레이어드컷 컬펌의 볼륨감 강화\n\n레이어드컷 컬펌은 볼륨감을 극대화하여 스타일을 더욱 풍성하게 만들어줍니다. 이 스타일은 기본적으로 다층적인 컷을 통해 볼륨을 더해주며, 특히 긴머리 스타일에 잘 어울립니다. 결과적으로 여성들이 데일리 스타일로 많이 선택할 수 있는 요소를 제공합니다.\n\n## 모발 손상 최소화를 통한 건강한 스타일링\n\n레이어드컷 컬펌은 모발 손상을 최소화하는 데 중점을 두고 디자인되었습니다. 이는 건강한 모발을 유지하면서도 다양한 스타일을 시도할 수 있도록 해줍니다. 이 스타일은 적절한 관리와 올바른 제품 사용을 통해 모발 건강을 최우선으로 고려합니다.\n\n## 세련된 느낌의 다용도 스타일\n\n레이어드컷 컬펌은 다양한 자리에서 어울리는 세련된 느낌을 줍니다. 직장인부터 캐주얼한 분위기를 원하는 개인까지, 이 스타일은 누구에게나 자연스럽게 잘 어울립니다. 그 결과, 고객들은 이 스타일을 선택함으로써 편안하면서도 프로페셔널한 이미지를 구축할 수 있습니다.\n\n## 자연스러운 컬의 인기도\n\n자연스러운 컬을 생성하는 레이어드컷 컬펌은 고급스러운 이미지를 연출하며, 고객들의 높은 선호도를 얻고 있습니다. 이 컬은 어색하지 않고 부드러운 웨이브 형태로, 다양한 얼굴형과 스타일에 잘 맞습니다.\n\n## 가벼운 헤어 제품과의 호환성\n\n레이어드컷 컬펌은 가벼운 헤어 제품과 잘 어울려 스타일링의 용이함을 증가시킵니다. 고객들은 특수한 헤어 보조 제품을 사용하지 않고도 간편하게 원하는 스타일을 완성할 수 있어, 바쁜 일상에서도 접근성이 높습니다.\n\n## 겨울철 모발 관리에 적합\n\n겨울철에 효과적인 모발 관리가 가능한 레이어드컷 컬펌은 겨울철 낮은 습도와 차가운 날씨에 적합하여 더욱 추천될 수 있습니다. 이 스타일은 특히 건조한 계절에도 모발의 윤기를 유지하는 데 도움이 됩니다.\n\n## 부지런한 스타일링을 위한 최적의 선택\n\n레이어드컷 컬펌은 부지런한 스타일링을 통해 빠르고 간편하게 원하는 룩을 완성할 수 있도록 돕습니다. 이는 바쁜 사람들에게 적합한 선택이 되며, 적절한 관리로 스타일 유지가 용이합니다.",
    "report_json": {
      "title": "레이어드컷 컬펌 스타일 커뮤니티",
      "summary": "이 커뮤니티는 레이어드컷 컬펌을 중심으로 다양한 헤어 스타일 요소와 관리 방법을 포함하고 있으며, 여성들 사이에서의 인기와 세련됨을 강조합니다. 이 스타일은 모발 손상을 최소화하고 자연스러운 컬을 연출할 수 있는 특징을 가지고 있어 바쁜 일상 속에서도 손쉽게 활용할 수 있습니다.",
      "rating": 9.0,
      "rating_explanation": "레이어드컷 컬펌의 다양한 조합과 여성들 사이의 높은 선호도로 인해 이 스타일의 영향력이 미치는 범위가 넓고 매우 긍정적입니다.",
      "findings": [
        {
          "summary": "레이어드컷 컬펌의 볼륨감 강화",
          "explanation": "레이어드컷 컬펌은 볼륨감을 극대화하여 스타일을 더욱 풍성하게 만들어줍니다. 이 스타일은 기본적으로 다층적인 컷을 통해 볼륨을 더해주며, 특히 긴머리 스타일에 잘 어울립니다. 결과적으로 여성들이 데일리 스타일로 많이 선택할 수 있는 요소를 제공합니다."
        },
        {
          "summary": "모발 손상 최소화를 통한 건강한 스타일링",
          "explanation": "레이어드컷 컬펌은 모발 손상을 최소화하는 데 중점을 두고 디자인되었습니다. 이는 건강한 모발을 유지하면서도 다양한 스타일을 시도할 수 있도록 해줍니다. 이 스타일은 적절한 관리와 올바른 제품 사용을 통해 모발 건강을 최우선으로 고려합니다."
        },
        {
          "summary": "세련된 느낌의 다용도 스타일",
          "explanation": "레이어드컷 컬펌은 다양한 자리에서 어울리는 세련된 느낌을 줍니다. 직장인부터 캐주얼한 분위기를 원하는 개인까지, 이 스타일은 누구에게나 자연스럽게 잘 어울립니다. 그 결과, 고객들은 이 스타일을 선택함으로써 편안하면서도 프로페셔널한 이미지를 구축할 수 있습니다."
        },
        {
          "summary": "자연스러운 컬의 인기도",
          "explanation": "자연스러운 컬을 생성하는 레이어드컷 컬펌은 고급스러운 이미지를 연출하며, 고객들의 높은 선호도를 얻고 있습니다. 이 컬은 어색하지 않고 부드러운 웨이브 형태로, 다양한 얼굴형과 스타일에 잘 맞습니다."
        },
        {
          "summary": "가벼운 헤어 제품과의 호환성",
          "explanation": "레이어드컷 컬펌은 가벼운 헤어 제품과 잘 어울려 스타일링의 용이함을 증가시킵니다. 고객들은 특수한 헤어 보조 제품을 사용하지 않고도 간편하게 원하는 스타일을 완성할 수 있어, 바쁜 일상에서도 접근성이 높습니다."
        },
        {
          "summary": "겨울철 모발 관리에 적합",
          "explanation": "겨울철에 효과적인 모발 관리가 가능한 레이어드컷 컬펌은 겨울철 낮은 습도와 차가운 날씨에 적합하여 더욱 추천될 수 있습니다. 이 스타일은 특히 건조한 계절에도 모발의 윤기를 유지하는 데 도움이 됩니다."
        },
        {
          "summary": "부지런한 스타일링을 위한 최적의 선택",
          "explanation": "레이어드컷 컬펌은 부지런한 스타일링을 통해 빠르고 간편하게 원하는 룩을 완성할 수 있도록 돕습니다. 이는 바쁜 사람들에게 적합한 선택이 되며, 적절한 관리로 스타일 유지가 용이합니다."
        }
      ]
    },
    "level": 0,
    "title": "Cluster 8",
    "edges": [
      [
        "\"레이어드컷 컬펌\"",
        "\"손질 난이도 보통\""
      ],
      [
        "\"레이어드컷 컬펌\"",
        "\"부지런한 스타일링\""
      ],
      [
        "\"레이어드 컬펌\"",
        "\"볼륨 스프레이\""
      ],
      [
        "\"레이어드컷 컬펌\"",
        "\"여성들\""
      ],
      [
        "\"가벼운 헤어 제품\"",
        "\"레이어드컷 컬펌\""
      ],
      [
        "\"레이어드컷 컬펌\"",
        "\"보통 두께의 모발\""
      ],
      [
        "\"레이어드컷 컬펌\"",
        "\"반곱슬 모발\""
      ],
      [
        "\"모발 손상 최소화\"",
        "\"화장품 사용\""
      ],
      [
        "\"레이어드컷 컬펌\"",
        "\"모발 손상 최소화\""
      ],
      [
        "\"레이어드컷 컬펌\"",
        "\"부슬부슬한 모발\""
      ],
      [
        "\"레이어드 컬펌\"",
        "\"자연스러운 컬\""
      ],
      [
        "\"레이어드컷 컬펌\"",
        "\"자연스러운 분위기\""
      ],
      [
        "\"레이어드컷 컬펌\"",
        "\"볼륨감\""
      ],
      [
        "\"긴머리\"",
        "\"레이어드컷 컬펌\""
      ],
      [
        "\"레이어드컷 컬펌\"",
        "\"자연스러운 컬\""
      ],
      [
        "\"레이어드컷 컬펌\"",
        "\"세련된 느낌\""
      ],
      [
        "\"레이어드컷 컬펌\"",
        "\"부시시한 머리카락\""
      ],
      [
        "\"드라이어\"",
        "\"레이어드컷 컬펌\""
      ],
      [
        "\"레이어드컷 컬펌\"",
        "\"직장인\""
      ],
      [
        "\"겨울철 모발 관리\"",
        "\"레이어드컷 컬펌\""
      ],
      [
        "\"레이어드컷 컬펌\"",
        "\"짜임새 있는 머리\""
      ],
      [
        "\"레이어드컷 컬펌\"",
        "\"추가적인 레이어\""
      ]
    ],
    "nodes": [
      "\"부슬부슬한 모발\"",
      "\"모발 손상 최소화\"",
      "\"여성들\"",
      "\"추가적인 레이어\"",
      "\"부시시한 머리카락\"",
      "\"부지런한 스타일링\"",
      "\"겨울철 모발 관리\"",
      "\"자연스러운 컬\"",
      "\"가벼운 헤어 제품\"",
      "\"자연스러운 분위기\"",
      "\"손질 난이도 보통\"",
      "\"화장품 사용\"",
      "\"직장인\"",
      "\"짜임새 있는 머리\"",
      "\"반곱슬 모발\"",
      "\"보통 두께의 모발\"",
      "\"레이어드 컬펌\"",
      "\"긴머리\"",
      "\"레이어드컷 컬펌\"",
      "\"볼륨 스프레이\"",
      "\"드라이어\""
    ],
    "chunk_ids": [
      "chunk-aa3286f7d8b8f5afc0b3db44ded13e3f",
      "chunk-c133af03a51e41eab158f1bb61816b50",
      "chunk-3a88d84a6b27608aa907ee80770e479c",
      "chunk-6537c051bb955b20213bcfacafe0ae23"
    ],
    "occurrence": 1.0,
    "sub_communities": [
      "19",
      "20",
      "21"
    ]
  },
  "2": {
    "report_string": "# 남성 가일펌 및 긴 얼굴형 스타일 커뮤니티\n\n이 커뮤니티는 남성 가일펌과 긴 얼굴형을 갖춘 스타일의 조합을 중심으로 형성됩니다. '남자 가일펌', '위례 가일펌', '아이롱펌'과 같은 다양한 스타일이 긴 얼굴형과의 조화를 이루며, 깔끔한 분위기의 표현이 돋보입니다.\n\n## 긴 얼굴형에 적합한 레이어드펌\n\n긴 얼굴형의 경우 레이어드펌이 볼륨감을 더욱 부여하여 부드러운 인상을 줄 수 있습니다. 이러한 조합은 특히 얼굴형에 맞게 적절한 양을 조절하여 스타일링할 수 있다는 점에서 큰 장점이 있습니다.\n\n## 남자 가일펌과 위례 가일펌의 스타일 호환성\n\n남자 가일펌과 위례 가일펌은 스타일적으로 유사하여 서로 조화롭게 조합할 수 있습니다. 두 스타일은 도시적이고 세련된 이미지를 제공하며, 다양한 상황에서 활용되기에 적합합니다.\n\n## 남자 가일펌의 깔끔한 분위기\n\n남자 가일펌은 그 자체로도 깔끔한 분위기를 주며 연출하기 쉽습니다. 이는 직장 및 다양한 사회적 상황에 적합한 선택이 되어줍니다.\n\n## 곱슬머리와 남자 가일펌의 적합성\n\n남자 가일펌은 곱슬머리에도 적합하여 매력적인 스타일을 연출할 수 있습니다. 이는 스타일링 시 깔끔한 느낌을 제공하고, 길이나 디테일에 따라 다채로운 변형도 가능합니다.\n\n## 긴 얼굴형과 리프펌 스타일링의 조화\n\n리프펌은 긴 얼굴형에 적합하여 스타일 추천군에 포함됩니다. 이 스타일은 긴 얼굴을 더욱 세련되게 보완하며, 적절한 볼륨감을 추가하여 협조로운 이미지를 제공합니다.",
    "report_json": {
      "title": "남성 가일펌 및 긴 얼굴형 스타일 커뮤니티",
      "summary": "이 커뮤니티는 남성 가일펌과 긴 얼굴형을 갖춘 스타일의 조합을 중심으로 형성됩니다. '남자 가일펌', '위례 가일펌', '아이롱펌'과 같은 다양한 스타일이 긴 얼굴형과의 조화를 이루며, 깔끔한 분위기의 표현이 돋보입니다.",
      "rating": 7.5,
      "rating_explanation": "남성 선호 헤어스타일 중에서 가일펌의 인기와 긴 얼굴형을 고려한 스타일 조합으로 인해 상대적으로 높은 점수를 부여했습니다.",
      "findings": [
        {
          "summary": "긴 얼굴형에 적합한 레이어드펌",
          "explanation": "긴 얼굴형의 경우 레이어드펌이 볼륨감을 더욱 부여하여 부드러운 인상을 줄 수 있습니다. 이러한 조합은 특히 얼굴형에 맞게 적절한 양을 조절하여 스타일링할 수 있다는 점에서 큰 장점이 있습니다."
        },
        {
          "summary": "남자 가일펌과 위례 가일펌의 스타일 호환성",
          "explanation": "남자 가일펌과 위례 가일펌은 스타일적으로 유사하여 서로 조화롭게 조합할 수 있습니다. 두 스타일은 도시적이고 세련된 이미지를 제공하며, 다양한 상황에서 활용되기에 적합합니다."
        },
        {
          "summary": "남자 가일펌의 깔끔한 분위기",
          "explanation": "남자 가일펌은 그 자체로도 깔끔한 분위기를 주며 연출하기 쉽습니다. 이는 직장 및 다양한 사회적 상황에 적합한 선택이 되어줍니다."
        },
        {
          "summary": "곱슬머리와 남자 가일펌의 적합성",
          "explanation": "남자 가일펌은 곱슬머리에도 적합하여 매력적인 스타일을 연출할 수 있습니다. 이는 스타일링 시 깔끔한 느낌을 제공하고, 길이나 디테일에 따라 다채로운 변형도 가능합니다."
        },
        {
          "summary": "긴 얼굴형과 리프펌 스타일링의 조화",
          "explanation": "리프펌은 긴 얼굴형에 적합하여 스타일 추천군에 포함됩니다. 이 스타일은 긴 얼굴을 더욱 세련되게 보완하며, 적절한 볼륨감을 추가하여 협조로운 이미지를 제공합니다."
        }
      ]
    },
    "level": 0,
    "title": "Cluster 2",
    "edges": [
      [
        "\"긴 얼굴형\"",
        "\"레이어드펌\""
      ],
      [
        "\"남자 가일펌\"",
        "\"아이롱펌\""
      ],
      [
        "\"긴 얼굴형\"",
        "\"리프펌\""
      ],
      [
        "\"긴 얼굴형\"",
        "\"위례 가일펌\""
      ],
      [
        "\"남자 가일펌\"",
        "\"위례 가일펌\""
      ],
      [
        "\"깔끔한 분위기\"",
        "\"남자 가일펌\""
      ],
      [
        "\"곱슬머리\"",
        "\"남자 가일펌\""
      ]
    ],
    "nodes": [
      "\"깔끔한 분위기\"",
      "\"긴 얼굴형\"",
      "\"남자 가일펌\"",
      "\"위례 가일펌\"",
      "\"곱슬머리\"",
      "\"아이롱펌\""
    ],
    "chunk_ids": [
      "chunk-aa3286f7d8b8f5afc0b3db44ded13e3f",
      "chunk-c133af03a51e41eab158f1bb61816b50",
      "chunk-26f0ef8ea2f7ad3255c67cac5e87a11a",
      "chunk-3a88d84a6b27608aa907ee80770e479c"
    ],
    "occurrence": 1.0,
    "sub_communities": []
  },
  "5": {
    "report_string": "# 중년 허쉬레이어드 컬펌 스타일 커뮤니티\n\n이 커뮤니티는 중년 허쉬레이어드 컬펌을 중심으로 볼륨감, 동안 효과 등을 강하게 부각하는 다양한 스타일 요소들이 결합되어 있습니다. 이 스타일들이 상호작용하여 세련되고 젊어 보이는 헤어스타일을 창출하는 데 기여합니다.\n\n## 중년 허쉬레이어드 컬펌의 볼륨 강점\n\n중년 허쉬레이어드 컬펌은 볼륨감 있는 굵은 모발과 어깨 아래 길이에 어울리는 웨이브 스타일로, 풍성한 헤어스타일을 연출할 수 있습니다. 이는 특히 중년층에서 인기를 얻고 있으며, 목소리와 얼굴형에 맞춰 조정할 수도 있어 다양하게 활용 가능합니다.\n\n## 동안 효과를 극대화하는 스타일\n\n중년 허쉬레이어드 컬펌은 얼굴선을 감싸는 스타일로 동안 효과를 높입니다. 고객들은 이 스타일을 통해 젊어 보이는 인상을 받을 수 있으며, 이는 소비자들이 헤어스타일을 선택할 때 중요하게 생각하는 반복적인 트렌드 중 하나입니다.\n\n## 부드러운 곡선으로 우아한 이미지 창출\n\n이 스타일은 부드러운 곡선을 강조하여 우아하고 세련된 이미지를 만들어냅니다. 고급스러운 느낌을 주는 이러한 요소는 특별한 자리나 공식적인 행사에서 더욱 빛을 발할 수 있습니다.\n\n## 숱이 많은 머리 스타일 적합성\n\n중년 허쉬레이어드 컬펌은 숱이 많은 머리에 아주 잘 어울립니다. 풍성한 머리카락 특성을 가진 이 스타일은 볼륨감과 움직임을 제공하여 시각적으로 매력적인 효과를 줍니다.\n\n## 자연스러운 웨이브의 효과\n\n자연스러운 웨이브는 볼륨감을 강조할 수 있으며, 중년 허쉬레이어드 컬펌의 더 큰 매력을 더해줍니다. 이는 고객이 추가적인 스타일 요소를 원할 때 매우 유용한 조합입니다.",
    "report_json": {
      "title": "중년 허쉬레이어드 컬펌 스타일 커뮤니티",
      "summary": "이 커뮤니티는 중년 허쉬레이어드 컬펌을 중심으로 볼륨감, 동안 효과 등을 강하게 부각하는 다양한 스타일 요소들이 결합되어 있습니다. 이 스타일들이 상호작용하여 세련되고 젊어 보이는 헤어스타일을 창출하는 데 기여합니다.",
      "rating": 8.5,
      "rating_explanation": "중년 허쉬레이어드 컬펌은 여러 가지 강력한 특성과 효과가 결합된 스타일로, 높은 선호도와 추천도가 있으므로 높은 점수를 부여했습니다.",
      "findings": [
        {
          "summary": "중년 허쉬레이어드 컬펌의 볼륨 강점",
          "explanation": "중년 허쉬레이어드 컬펌은 볼륨감 있는 굵은 모발과 어깨 아래 길이에 어울리는 웨이브 스타일로, 풍성한 헤어스타일을 연출할 수 있습니다. 이는 특히 중년층에서 인기를 얻고 있으며, 목소리와 얼굴형에 맞춰 조정할 수도 있어 다양하게 활용 가능합니다."
        },
        {
          "summary": "동안 효과를 극대화하는 스타일",
          "explanation": "중년 허쉬레이어드 컬펌은 얼굴선을 감싸는 스타일로 동안 효과를 높입니다. 고객들은 이 스타일을 통해 젊어 보이는 인상을 받을 수 있으며, 이는 소비자들이 헤어스타일을 선택할 때 중요하게 생각하는 반복적인 트렌드 중 하나입니다."
        },
        {
          "summary": "부드러운 곡선으로 우아한 이미지 창출",
          "explanation": "이 스타일은 부드러운 곡선을 강조하여 우아하고 세련된 이미지를 만들어냅니다. 고급스러운 느낌을 주는 이러한 요소는 특별한 자리나 공식적인 행사에서 더욱 빛을 발할 수 있습니다."
        },
        {
          "summary": "숱이 많은 머리 스타일 적합성",
          "explanation": "중년 허쉬레이어드 컬펌은 숱이 많은 머리에 아주 잘 어울립니다. 풍성한 머리카락 특성을 가진 이 스타일은 볼륨감과 움직임을 제공하여 시각적으로 매력적인 효과를 줍니다."
        },
        {
          "summary": "자연스러운 웨이브의 효과",
          "explanation": "자연스러운 웨이브는 볼륨감을 강조할 수 있으며, 중년 허쉬레이어드 컬펌의 더 큰 매력을 더해줍니다. 이는 고객이 추가적인 스타일 요소를 원할 때 매우 유용한 조합입니다."
        }
      ]
    },
    "level": 0,
    "title": "Cluster 5",
    "edges": [
      [
        "\"동안 효과\"",
        "\"중년 허쉬레이어드 컬펌\""
      ],
      [
        "\"동안 효과\"",
        "\"레이어드펌\""
      ],
      [
        "\"숱이 많은 머리\"",
        "\"중년 허쉬레이어드 컬펌\""
      ],
      [
        "\"레이어드컷 컬펌\"",
        "\"볼륨감\""
      ],
      [
        "\"부드러운 곡선\"",
        "\"중년 허쉬레이어드 컬펌\""
      ],
      [
        "\"볼륨감\"",
        "\"자연스러운 웨이브\""
      ],
      [
        "\"볼륨감\"",
        "\"중년 허쉬레이어드 컬펌\""
      ]
    ],
    "nodes": [
      "\"볼륨감\"",
      "\"부드러운 곡선\"",
      "\"중년 허쉬레이어드 컬펌\"",
      "\"자연스러운 웨이브\"",
      "\"동안 효과\"",
      "\"숱이 많은 머리\""
    ],
    "chunk_ids": [
      "chunk-c133af03a51e41eab158f1bb61816b50",
      "chunk-3a88d84a6b27608aa907ee80770e479c"
    ],
    "occurrence": 0.5,
    "sub_communities": []
  },
  "7": {
    "report_string": "# 핵심 헤어스타일 커뮤니티: 히피펌과 가르마펌\n\n이 커뮤니티는 다양한 헤어스타일 요소로 구성되어 있으며, 특히 히피펌과 가르마펌이 중심적인 역할을 하고 있습니다. 각 헤어스타일은 특정 모발 유형과 얼굴형에 맞춰 추천되며, 서로의 특성과 연결되어 다양한 스타일링 가능성을 제공합니다.\n\n## 히피펌의 독창성과 개성\n\n히피펌은 개성적인 스타일을 선호하는 고객들에게 적합한 다양한 웨이브로 특징지어집니다. 이 스타일은 특히 자연스러운 컬을 통해 사람들의 독창적인 이미지를 강조하며, 다양한 페이스형과 조화를 이루기도 합니다. 하지만 웨이브가 많은 특성으로 인해 관리가 까다로운 점은 주의해야 할 부분입니다.\n\n## 가는 모발에 적합한 스타일링\n\n가는 모발을 가진 고객들은 히피펌과 가르마펌과 같은 스타일을 통해 자연스러운 볼륨을 더할 수 있습니다. 가는 모발은 유연하고 가볍기로 특징지어지기 때문에, 이러한 스타일들은 보다 풍성한 외관을 연출할 수 있도록 돕습니다. 또한, 이러한 스타일은 고객의 모발 상태에 따라 조정하여 최적의 결과를 낼 수 있습니다.\n\n## 광대가 발달한 얼굴형과의 조합\n\n히피펌은 광대가 발달한 얼굴형을 가진 고객에게 매우 잘 어울리는 스타일로 평가됩니다. 이 스타일은 얼굴형의 특징을 부드럽게 감싸주면서도 특유의 개성을 돋보이게 하여, 고객이 자신감을 가질 수 있도록 도와줍니다.\n\n## 가르마펌의 도시적 이미지\n\n가르마펌은 깔끔한 이미지를 선사하며, 남성들에게 특히 인기가 높습니다. 이 스타일은 가르는 방식에 따라 다양한 분위기를 연출할 수 있으며, 자연스럽게 흘러내리는 효과를 통해 도시적인 느낌을 강조합니다. 직모를 가진 고객들에게 특히 추천될 수 있는 스타일입니다.\n\n## 스타일 간의 조합과 추천\n\n가일 포마드펌은 포마드펌과 매우 밀접하게 연결되어 있어 두 스타일이 함께 추천되는 경향이 있습니다. 이 조합은 고객에게 다양한 스타일링 선택지를 제공하며, 필요한 경우 두 스타일을 적절히 조합하여 더욱 세련된 이미지를 만들어 낼 수 있습니다.",
    "report_json": {
      "title": "핵심 헤어스타일 커뮤니티: 히피펌과 가르마펌",
      "summary": "이 커뮤니티는 다양한 헤어스타일 요소로 구성되어 있으며, 특히 히피펌과 가르마펌이 중심적인 역할을 하고 있습니다. 각 헤어스타일은 특정 모발 유형과 얼굴형에 맞춰 추천되며, 서로의 특성과 연결되어 다양한 스타일링 가능성을 제공합니다.",
      "rating": 7.5,
      "rating_explanation": "각 헤어스타일은 특정 타겟 고객층과 연관되어 추천되며, 특히 젊은 세대에게 인기가 있는 트렌디한 스타일들이 포함되어 있습니다.",
      "findings": [
        {
          "summary": "히피펌의 독창성과 개성",
          "explanation": "히피펌은 개성적인 스타일을 선호하는 고객들에게 적합한 다양한 웨이브로 특징지어집니다. 이 스타일은 특히 자연스러운 컬을 통해 사람들의 독창적인 이미지를 강조하며, 다양한 페이스형과 조화를 이루기도 합니다. 하지만 웨이브가 많은 특성으로 인해 관리가 까다로운 점은 주의해야 할 부분입니다."
        },
        {
          "summary": "가는 모발에 적합한 스타일링",
          "explanation": "가는 모발을 가진 고객들은 히피펌과 가르마펌과 같은 스타일을 통해 자연스러운 볼륨을 더할 수 있습니다. 가는 모발은 유연하고 가볍기로 특징지어지기 때문에, 이러한 스타일들은 보다 풍성한 외관을 연출할 수 있도록 돕습니다. 또한, 이러한 스타일은 고객의 모발 상태에 따라 조정하여 최적의 결과를 낼 수 있습니다."
        },
        {
          "summary": "광대가 발달한 얼굴형과의 조합",
          "explanation": "히피펌은 광대가 발달한 얼굴형을 가진 고객에게 매우 잘 어울리는 스타일로 평가됩니다. 이 스타일은 얼굴형의 특징을 부드럽게 감싸주면서도 특유의 개성을 돋보이게 하여, 고객이 자신감을 가질 수 있도록 도와줍니다."
        },
        {
          "summary": "가르마펌의 도시적 이미지",
          "explanation": "가르마펌은 깔끔한 이미지를 선사하며, 남성들에게 특히 인기가 높습니다. 이 스타일은 가르는 방식에 따라 다양한 분위기를 연출할 수 있으며, 자연스럽게 흘러내리는 효과를 통해 도시적인 느낌을 강조합니다. 직모를 가진 고객들에게 특히 추천될 수 있는 스타일입니다."
        },
        {
          "summary": "스타일 간의 조합과 추천",
          "explanation": "가일 포마드펌은 포마드펌과 매우 밀접하게 연결되어 있어 두 스타일이 함께 추천되는 경향이 있습니다. 이 조합은 고객에게 다양한 스타일링 선택지를 제공하며, 필요한 경우 두 스타일을 적절히 조합하여 더욱 세련된 이미지를 만들어 낼 수 있습니다."
        }
      ]
    },
    "level": 0,
    "title": "Cluster 7",
    "edges": [
      [
        "\"가일 포마드펌\"",
        "\"포마드펌\""
      ],
      [
        "\"가일 포마드펌\"",
        "\"짧은 앞머리\""
      ],
      [
        "\"리프컷펌\"",
        "\"직모\""
      ],
      [
        "\"가는 모발\"",
        "\"스핀스왈로펌\""
      ],
      [
        "\"관리의 까다로움\"",
        "\"히피펌\""
      ],
      [
        "\"부드러운 느낌\"",
        "\"스핀스왈로펌\""
      ],
      [
        "\"젊고 개성적인 스타일\"",
        "\"히피펌\""
      ],
      [
        "\"가일컷\"",
        "\"직모\""
      ],
      [
        "\"가르마펌\"",
        "\"직모\""
      ],
      [
        "\"가는 모발\"",
        "\"히피펌\""
      ],
      [
        "\"광대가 발달한 얼굴형\"",
        "\"히피펌\""
      ],
      [
        "\"가는 모발\"",
        "\"가르마펌\""
      ],
      [
        "\"부드러운 느낌\"",
        "\"포마드펌\""
      ],
      [
        "\"가일 포마드펌\"",
        "\"볼륨감 있는 웨이브\""
      ],
      [
        "\"리프컷펌\"",
        "\"부드러운 느낌\""
      ]
    ],
    "nodes": [
      "\"부드러운 느낌\"",
      "\"가는 모발\"",
      "\"광대가 발달한 얼굴형\"",
      "\"리프컷펌\"",
      "\"볼륨감 있는 웨이브\"",
      "\"관리의 까다로움\"",
      "\"가일 포마드펌\"",
      "\"스핀스왈로펌\"",
      "\"짧은 앞머리\"",
      "\"직모\"",
      "\"포마드펌\"",
      "\"젊고 개성적인 스타일\"",
      "\"히피펌\""
    ],
    "chunk_ids": [
      "chunk-aa3286f7d8b8f5afc0b3db44ded13e3f",
      "chunk-26f0ef8ea2f7ad3255c67cac5e87a11a",
      "chunk-6537c051bb955b20213bcfacafe0ae23"
    ],
    "occurrence": 0.75,
    "sub_communities": [
      "16",
      "17",
      "18"
    ]
  },
  "3": {
    "report_string": "# 가일컷 중심 헤어스타일 커뮤니티\n\n이 커뮤니티는 가일컷을 중심으로 다양한 헤어 스타일 및 특징 요소들이 조화롭게 결합되어 있으며, 특히 직모와 굵은 모발에 잘 어울리는 스타일링 방안으로 구성되어 있습니다. 유지 및 관리가 용이한 스타일과 얼굴형 보완 효과를 제공하는 다양한 조합이 돋보입니다.\n\n## 가일컷과 직모 조화\n\n가일컷은 직모에 최적화된 스타일로, 자연스러운 헤어라인을 형성하며 단정한 느낌을 연출합니다. 직모는 이 스타일의 특징을 극대화하여 깔끔하고 시원한 이미지를 주기 때문에 고객들의 선호도가 높습니다.\n\n## 가일컷과 필러스컷의 스타일링 다양성\n\n가일컷과 필러스컷은 함께 사용될 수 있으며, 이 조합은 서로 다른 스타일링 접근을 가능하게 합니다. 필러스컷은 자연스럽게 떨어지는 앞쪽 머리 스타일로, 가일컷을 보완하여 더욱 소프트한 이미지를 연출할 수 있습니다.\n\n## 가일컷과 다운펌의 세련된 매력\n\n가일컷은 다운펌과 함께 시술될 때 더욱 깔끔한 댄디 스타일을 완성합니다. 다운펌은 뿌리를 눌러 부드럽고 정돈된 느낌을 주며, 이렇게 결합된 스타일은 직장인들에게 특히 인기가 있습니다.\n\n## 리프팅 효과와 가일컷의 조화\n\n가일컷은 볼륨감을 높이고 얼굴형을 보완하는 리프팅 효과가 있습니다. 이 효과는 특히 얼굴을 작아 보이게 하고, 보다 세련된 이미지를 줄 수 있어 많은 고객들이 선호됩니다.\n\n## 성숙하고 깔끔한 분위기 제공\n\n가일컷은 성숙한 이미지를 주면서도 여전히 깔끔한 인상을 주는 스타일로, 능동적인 고객들에게 잘 어울립니다. 이 스타일은 특히 직장 환경에서도 적합하여 광범위한 연령층에서 인기입니다.\n\n## 앞머리 길이 조절 가능성\n\n가일컷은 앞머리의 길이를 조절하여 다양한 이미지를 연출할 수 있는 특징이 있습니다. 이로 인해 고객은 자신의 얼굴형과 스타일에 맞는 최적의 길이를 선택할 수 있어 맞춤형 스타일링이 가능합니다.\n\n## 헤어라인 가리기 기능\n\n가일컷은 이마와 헤어라인을 효과적으로 가려주어 보다 단정한 느낌을 줄 수 있습니다. 이 스타일은 이마가 넓은 고객들에게 특히 추천되며, 쉽게 자연스럽게 스타일을 만들 수 있는 장점이 있습니다.",
    "report_json": {
      "title": "가일컷 중심 헤어스타일 커뮤니티",
      "summary": "이 커뮤니티는 가일컷을 중심으로 다양한 헤어 스타일 및 특징 요소들이 조화롭게 결합되어 있으며, 특히 직모와 굵은 모발에 잘 어울리는 스타일링 방안으로 구성되어 있습니다. 유지 및 관리가 용이한 스타일과 얼굴형 보완 효과를 제공하는 다양한 조합이 돋보입니다.",
      "rating": 8.5,
      "rating_explanation": "가일컷이 인기 있는 스타일이며, 다양한 관리 용이성과 얼굴형 보완 특성 덕분에 많은 추천을 받고 있는 커뮤니티이므로 높은 점수를 부여했습니다.",
      "findings": [
        {
          "summary": "가일컷과 직모 조화",
          "explanation": "가일컷은 직모에 최적화된 스타일로, 자연스러운 헤어라인을 형성하며 단정한 느낌을 연출합니다. 직모는 이 스타일의 특징을 극대화하여 깔끔하고 시원한 이미지를 주기 때문에 고객들의 선호도가 높습니다."
        },
        {
          "summary": "가일컷과 필러스컷의 스타일링 다양성",
          "explanation": "가일컷과 필러스컷은 함께 사용될 수 있으며, 이 조합은 서로 다른 스타일링 접근을 가능하게 합니다. 필러스컷은 자연스럽게 떨어지는 앞쪽 머리 스타일로, 가일컷을 보완하여 더욱 소프트한 이미지를 연출할 수 있습니다."
        },
        {
          "summary": "가일컷과 다운펌의 세련된 매력",
          "explanation": "가일컷은 다운펌과 함께 시술될 때 더욱 깔끔한 댄디 스타일을 완성합니다. 다운펌은 뿌리를 눌러 부드럽고 정돈된 느낌을 주며, 이렇게 결합된 스타일은 직장인들에게 특히 인기가 있습니다."
        },
        {
          "summary": "리프팅 효과와 가일컷의 조화",
          "explanation": "가일컷은 볼륨감을 높이고 얼굴형을 보완하는 리프팅 효과가 있습니다. 이 효과는 특히 얼굴을 작아 보이게 하고, 보다 세련된 이미지를 줄 수 있어 많은 고객들이 선호됩니다."
        },
        {
          "summary": "성숙하고 깔끔한 분위기 제공",
          "explanation": "가일컷은 성숙한 이미지를 주면서도 여전히 깔끔한 인상을 주는 스타일로, 능동적인 고객들에게 잘 어울립니다. 이 스타일은 특히 직장 환경에서도 적합하여 광범위한 연령층에서 인기입니다."
        },
        {
          "summary": "앞머리 길이 조절 가능성",
          "explanation": "가일컷은 앞머리의 길이를 조절하여 다양한 이미지를 연출할 수 있는 특징이 있습니다. 이로 인해 고객은 자신의 얼굴형과 스타일에 맞는 최적의 길이를 선택할 수 있어 맞춤형 스타일링이 가능합니다."
        },
        {
          "summary": "헤어라인 가리기 기능",
          "explanation": "가일컷은 이마와 헤어라인을 효과적으로 가려주어 보다 단정한 느낌을 줄 수 있습니다. 이 스타일은 이마가 넓은 고객들에게 특히 추천되며, 쉽게 자연스럽게 스타일을 만들 수 있는 장점이 있습니다."
        }
      ]
    },
    "level": 0,
    "title": "Cluster 3",
    "edges": [
      [
        "\"가일컷\"",
        "\"필러스컷\""
      ],
      [
        "\"가일컷\"",
        "\"쉽게 관리할 수 있는 스타일\""
      ],
      [
        "\"가일컷\"",
        "\"프론트 오픈\""
      ],
      [
        "\"가일컷\"",
        "\"직모\""
      ],
      [
        "\"가일컷\"",
        "\"다운펌\""
      ],
      [
        "\"가일컷\"",
        "\"적당한 길이의 단발\""
      ],
      [
        "\"가일컷\"",
        "\"성숙하고 깔끔한 분위기\""
      ],
      [
        "\"가일컷\"",
        "\"이마가 넓은 얼굴형\""
      ],
      [
        "\"가일컷\"",
        "\"헤어라인 가리기\""
      ],
      [
        "\"관리 용이한 스타일\"",
        "\"필러스컷\""
      ],
      [
        "\"가일컷\"",
        "\"앞머리 길이 조절\""
      ],
      [
        "\"가일컷\"",
        "\"리프팅 효과\""
      ],
      [
        "\"가일컷\"",
        "\"굵은 모발\""
      ]
    ],
    "nodes": [
      "\"관리 용이한 스타일\"",
      "\"앞머리 길이 조절\"",
      "\"적당한 길이의 단발\"",
      "\"다운펌\"",
      "\"리프팅 효과\"",
      "\"쉽게 관리할 수 있는 스타일\"",
      "\"필러스컷\"",
      "\"헤어라인 가리기\"",
      "\"프론트 오픈\"",
      "\"성숙하고 깔끔한 분위기\"",
      "\"이마가 넓은 얼굴형\"",
      "\"굵은 모발\"",
      "\"가일컷\""
    ],
    "chunk_ids": [
      "chunk-aa3286f7d8b8f5afc0b3db44ded13e3f",
      "chunk-6537c051bb955b20213bcfacafe0ae23"
    ],
    "occurrence": 0.5,
    "sub_communities": [
      "12",
      "11"
    ]
  }
}